[
    {
        "box": [
            179,
            80,
            247,
            115
        ],
        "label": "background"
    },
    {
        "box": [
            55,
            169,
            83,
            181
        ],
        "label": "background"
    },
    {
        "box": [
            143,
            143,
            398,
            300
        ],
        "label": "background"
    },
    {
        "box": [
            0,
            142,
            398,
            300
        ],
        "label": "background"
    },
    {
        "box": [
            63,
            135,
            398,
            299
        ],
        "label": "background"
    },
    {
        "box": [
            0,
            64,
            4,
            192
        ],
        "label": "background"
    },
    {
        "box": [
            0,
            217,
            67,
            272
        ],
        "label": "background"
    },
    {
        "box": [
            4,
            0,
            397,
            174
        ],
        "label": "background"
    },
    {
        "box": [
            43,
            261,
            90,
            288
        ],
        "label": "pothole"
    },
    {
        "box": [
            4,
            171,
            107,
            300
        ],
        "label": "background"
    },
    {
        "box": [
            5,
            185,
            50,
            279
        ],
        "label": "background"
    },
    {
        "box": [
            0,
            240,
            16,
            300
        ],
        "label": "background"
    },
    {
        "box": [
            121,
            0,
            400,
            300
        ],
        "label": "background"
    },
    {
        "box": [
            198,
            244,
            210,
            259
        ],
        "label": "background"
    },
    {
        "box": [
            140,
            201,
            208,
            233
        ],
        "label": "background"
    },
    {
        "box": [
            345,
            50,
            372,
            59
        ],
        "label": "background"
    },
    {
        "box": [
            198,
            244,
            225,
            259
        ],
        "label": "background"
    },
    {
        "box": [
            46,
            0,
            160,
            47
        ],
        "label": "background"
    },
    {
        "box": [
            101,
            191,
            331,
            228
        ],
        "label": "background"
    },
    {
        "box": [
            362,
            0,
            398,
            48
        ],
        "label": "background"
    },
    {
        "box": [
            125,
            35,
            156,
            42
        ],
        "label": "background"
    },
    {
        "box": [
            361,
            0,
            398,
            104
        ],
        "label": "background"
    },
    {
        "box": [
            56,
            143,
            230,
            212
        ],
        "label": "pothole"
    },
    {
        "box": [
            373,
            104,
            399,
            164
        ],
        "label": "background"
    },
    {
        "box": [
            0,
            216,
            177,
            300
        ],
        "label": "background"
    },
    {
        "box": [
            10,
            0,
            160,
            47
        ],
        "label": "background"
    },
    {
        "box": [
            66,
            159,
            230,
            212
        ],
        "label": "pothole"
    },
    {
        "box": [
            0,
            0,
            16,
            240
        ],
        "label": "background"
    },
    {
        "box": [
            0,
            28,
            59,
            224
        ],
        "label": "background"
    },
    {
        "box": [
            6,
            30,
            156,
            74
        ],
        "label": "background"
    },
    {
        "box": [
            0,
            0,
            368,
            224
        ],
        "label": "background"
    },
    {
        "box": [
            398,
            80,
            400,
            178
        ],
        "label": "background"
    },
    {
        "box": [
            294,
            64,
            371,
            81
        ],
        "label": "background"
    },
    {
        "box": [
            294,
            88,
            328,
            96
        ],
        "label": "background"
    },
    {
        "box": [
            43,
            262,
            90,
            284
        ],
        "label": "background"
    },
    {
        "box": [
            219,
            80,
            247,
            95
        ],
        "label": "background"
    },
    {
        "box": [
            5,
            171,
            19,
            192
        ],
        "label": "background"
    },
    {
        "box": [
            91,
            143,
            174,
            178
        ],
        "label": "background"
    },
    {
        "box": [
            143,
            83,
            400,
            300
        ],
        "label": "background"
    },
    {
        "box": [
            0,
            273,
            15,
            300
        ],
        "label": "background"
    },
    {
        "box": [
            203,
            117,
            346,
            164
        ],
        "label": "background"
    },
    {
        "box": [
            362,
            0,
            398,
            80
        ],
        "label": "background"
    },
    {
        "box": [
            200,
            184,
            226,
            193
        ],
        "label": "background"
    },
    {
        "box": [
            391,
            0,
            400,
            178
        ],
        "label": "background"
    },
    {
        "box": [
            226,
            185,
            272,
            199
        ],
        "label": "background"
    },
    {
        "box": [
            237,
            231,
            255,
            245
        ],
        "label": "background"
    },
    {
        "box": [
            4,
            0,
            397,
            172
        ],
        "label": "background"
    },
    {
        "box": [
            179,
            83,
            398,
            172
        ],
        "label": "background"
    },
    {
        "box": [
            233,
            92,
            265,
            101
        ],
        "label": "background"
    },
    {
        "box": [
            362,
            43,
            397,
            67
        ],
        "label": "background"
    },
    {
        "box": [
            5,
            0,
            397,
            234
        ],
        "label": "background"
    },
    {
        "box": [
            5,
            175,
            21,
            208
        ],
        "label": "background"
    },
    {
        "box": [
            47,
            112,
            398,
            298
        ],
        "label": "background"
    },
    {
        "box": [
            0,
            0,
            48,
            240
        ],
        "label": "background"
    },
    {
        "box": [
            237,
            234,
            255,
            245
        ],
        "label": "background"
    },
    {
        "box": [
            5,
            184,
            10,
            279
        ],
        "label": "background"
    },
    {
        "box": [
            48,
            75,
            117,
            82
        ],
        "label": "background"
    },
    {
        "box": [
            5,
            170,
            156,
            294
        ],
        "label": "background"
    },
    {
        "box": [
            60,
            146,
            79,
            154
        ],
        "label": "background"
    },
    {
        "box": [
            55,
            140,
            267,
            226
        ],
        "label": "pothole"
    },
    {
        "box": [
            5,
            85,
            32,
            208
        ],
        "label": "background"
    },
    {
        "box": [
            148,
            161,
            270,
            206
        ],
        "label": "background"
    },
    {
        "box": [
            364,
            162,
            394,
            169
        ],
        "label": "background"
    },
    {
        "box": [
            224,
            204,
            281,
            219
        ],
        "label": "background"
    },
    {
        "box": [
            0,
            170,
            156,
            298
        ],
        "label": "background"
    },
    {
        "box": [
            151,
            27,
            184,
            36
        ],
        "label": "background"
    },
    {
        "box": [
            152,
            207,
            188,
            226
        ],
        "label": "background"
    },
    {
        "box": [
            179,
            83,
            398,
            129
        ],
        "label": "background"
    },
    {
        "box": [
            90,
            114,
            106,
            128
        ],
        "label": "background"
    },
    {
        "box": [
            217,
            157,
            250,
            181
        ],
        "label": "background"
    },
    {
        "box": [
            7,
            64,
            282,
            174
        ],
        "label": "background"
    },
    {
        "box": [
            233,
            70,
            331,
            110
        ],
        "label": "background"
    },
    {
        "box": [
            110,
            87,
            166,
            104
        ],
        "label": "background"
    },
    {
        "box": [
            187,
            187,
            209,
            198
        ],
        "label": "background"
    },
    {
        "box": [
            176,
            202,
            202,
            219
        ],
        "label": "background"
    },
    {
        "box": [
            286,
            212,
            302,
            226
        ],
        "label": "background"
    },
    {
        "box": [
            298,
            194,
            330,
            210
        ],
        "label": "background"
    },
    {
        "box": [
            90,
            114,
            107,
            128
        ],
        "label": "background"
    },
    {
        "box": [
            359,
            160,
            399,
            299
        ],
        "label": "background"
    },
    {
        "box": [
            226,
            183,
            271,
            200
        ],
        "label": "background"
    },
    {
        "box": [
            297,
            196,
            330,
            209
        ],
        "label": "background"
    },
    {
        "box": [
            234,
            43,
            398,
            112
        ],
        "label": "background"
    },
    {
        "box": [
            330,
            98,
            384,
            124
        ],
        "label": "background"
    },
    {
        "box": [
            58,
            186,
            83,
            205
        ],
        "label": "background"
    },
    {
        "box": [
            140,
            298,
            340,
            299
        ],
        "label": "background"
    },
    {
        "box": [
            0,
            64,
            4,
            96
        ],
        "label": "background"
    },
    {
        "box": [
            29,
            216,
            65,
            234
        ],
        "label": "background"
    },
    {
        "box": [
            5,
            30,
            59,
            56
        ],
        "label": "background"
    },
    {
        "box": [
            102,
            264,
            172,
            298
        ],
        "label": "pothole"
    },
    {
        "box": [
            152,
            27,
            185,
            37
        ],
        "label": "background"
    },
    {
        "box": [
            203,
            117,
            320,
            164
        ],
        "label": "background"
    },
    {
        "box": [
            7,
            67,
            282,
            174
        ],
        "label": "background"
    },
    {
        "box": [
            398,
            0,
            400,
            80
        ],
        "label": "background"
    },
    {
        "box": [
            0,
            273,
            4,
            300
        ],
        "label": "background"
    },
    {
        "box": [
            235,
            41,
            398,
            126
        ],
        "label": "background"
    },
    {
        "box": [
            136,
            115,
            180,
            147
        ],
        "label": "background"
    },
    {
        "box": [
            344,
            52,
            363,
            62
        ],
        "label": "background"
    },
    {
        "box": [
            128,
            113,
            180,
            139
        ],
        "label": "background"
    },
    {
        "box": [
            187,
            185,
            225,
            199
        ],
        "label": "background"
    },
    {
        "box": [
            101,
            203,
            172,
            226
        ],
        "label": "background"
    },
    {
        "box": [
            101,
            264,
            356,
            300
        ],
        "label": "background"
    },
    {
        "box": [
            3,
            0,
            4,
            300
        ],
        "label": "background"
    },
    {
        "box": [
            76,
            113,
            180,
            178
        ],
        "label": "background"
    },
    {
        "box": [
            360,
            161,
            394,
            168
        ],
        "label": "background"
    },
    {
        "box": [
            179,
            83,
            328,
            115
        ],
        "label": "background"
    },
    {
        "box": [
            5,
            104,
            399,
            298
        ],
        "label": "background"
    },
    {
        "box": [
            71,
            262,
            92,
            281
        ],
        "label": "background"
    },
    {
        "box": [
            198,
            244,
            211,
            259
        ],
        "label": "background"
    },
    {
        "box": [
            210,
            218,
            251,
            254
        ],
        "label": "background"
    },
    {
        "box": [
            217,
            158,
            251,
            181
        ],
        "label": "background"
    },
    {
        "box": [
            55,
            113,
            266,
            233
        ],
        "label": "background"
    },
    {
        "box": [
            240,
            213,
            279,
            224
        ],
        "label": "background"
    },
    {
        "box": [
            292,
            59,
            397,
            104
        ],
        "label": "background"
    },
    {
        "box": [
            198,
            218,
            251,
            259
        ],
        "label": "background"
    },
    {
        "box": [
            153,
            202,
            204,
            226
        ],
        "label": "background"
    },
    {
        "box": [
            179,
            43,
            398,
            112
        ],
        "label": "background"
    },
    {
        "box": [
            0,
            0,
            3,
            160
        ],
        "label": "background"
    },
    {
        "box": [
            72,
            156,
            214,
            212
        ],
        "label": "pothole"
    },
    {
        "box": [
            307,
            64,
            371,
            79
        ],
        "label": "background"
    },
    {
        "box": [
            134,
            119,
            173,
            148
        ],
        "label": "background"
    },
    {
        "box": [
            328,
            95,
            387,
            128
        ],
        "label": "background"
    },
    {
        "box": [
            5,
            38,
            23,
            69
        ],
        "label": "background"
    },
    {
        "box": [
            0,
            0,
            4,
            160
        ],
        "label": "background"
    },
    {
        "box": [
            215,
            48,
            398,
            206
        ],
        "label": "background"
    },
    {
        "box": [
            384,
            48,
            397,
            65
        ],
        "label": "background"
    },
    {
        "box": [
            373,
            160,
            398,
            206
        ],
        "label": "background"
    },
    {
        "box": [
            215,
            100,
            344,
            172
        ],
        "label": "background"
    },
    {
        "box": [
            95,
            209,
            125,
            219
        ],
        "label": "background"
    },
    {
        "box": [
            5,
            109,
            398,
            299
        ],
        "label": "background"
    },
    {
        "box": [
            361,
            0,
            397,
            65
        ],
        "label": "background"
    },
    {
        "box": [
            44,
            0,
            353,
            100
        ],
        "label": "background"
    },
    {
        "box": [
            5,
            144,
            32,
            173
        ],
        "label": "background"
    },
    {
        "box": [
            359,
            0,
            400,
            300
        ],
        "label": "background"
    },
    {
        "box": [
            0,
            0,
            3,
            300
        ],
        "label": "background"
    },
    {
        "box": [
            5,
            85,
            32,
            176
        ],
        "label": "background"
    },
    {
        "box": [
            139,
            139,
            276,
            226
        ],
        "label": "background"
    },
    {
        "box": [
            153,
            203,
            182,
            217
        ],
        "label": "background"
    },
    {
        "box": [
            92,
            263,
            177,
            300
        ],
        "label": "pothole"
    },
    {
        "box": [
            139,
            158,
            270,
            226
        ],
        "label": "background"
    },
    {
        "box": [
            5,
            0,
            48,
            38
        ],
        "label": "background"
    },
    {
        "box": [
            307,
            53,
            372,
            83
        ],
        "label": "background"
    },
    {
        "box": [
            215,
            141,
            276,
            166
        ],
        "label": "background"
    },
    {
        "box": [
            392,
            0,
            398,
            104
        ],
        "label": "background"
    },
    {
        "box": [
            244,
            213,
            279,
            224
        ],
        "label": "background"
    },
    {
        "box": [
            361,
            41,
            398,
            104
        ],
        "label": "background"
    },
    {
        "box": [
            55,
            115,
            230,
            219
        ],
        "label": "background"
    },
    {
        "box": [
            223,
            191,
            297,
            206
        ],
        "label": "background"
    },
    {
        "box": [
            55,
            113,
            180,
            181
        ],
        "label": "background"
    },
    {
        "box": [
            154,
            207,
            188,
            218
        ],
        "label": "background"
    },
    {
        "box": [
            66,
            118,
            249,
            219
        ],
        "label": "pothole"
    },
    {
        "box": [
            150,
            27,
            184,
            36
        ],
        "label": "background"
    },
    {
        "box": [
            176,
            173,
            213,
            199
        ],
        "label": "background"
    },
    {
        "box": [
            5,
            36,
            118,
            192
        ],
        "label": "background"
    },
    {
        "box": [
            95,
            263,
            177,
            300
        ],
        "label": "pothole"
    },
    {
        "box": [
            240,
            48,
            398,
            176
        ],
        "label": "background"
    },
    {
        "box": [
            398,
            0,
            400,
            160
        ],
        "label": "background"
    },
    {
        "box": [
            14,
            7,
            32,
            16
        ],
        "label": "background"
    },
    {
        "box": [
            179,
            83,
            325,
            115
        ],
        "label": "background"
    },
    {
        "box": [
            254,
            117,
            320,
            142
        ],
        "label": "background"
    },
    {
        "box": [
            5,
            37,
            28,
            75
        ],
        "label": "background"
    },
    {
        "box": [
            179,
            80,
            284,
            115
        ],
        "label": "background"
    },
    {
        "box": [
            356,
            0,
            400,
            300
        ],
        "label": "background"
    },
    {
        "box": [
            5,
            144,
            24,
            192
        ],
        "label": "background"
    },
    {
        "box": [
            244,
            95,
            391,
            154
        ],
        "label": "background"
    },
    {
        "box": [
            16,
            30,
            59,
            37
        ],
        "label": "background"
    },
    {
        "box": [
            0,
            217,
            86,
            300
        ],
        "label": "background"
    },
    {
        "box": [
            205,
            140,
            258,
            165
        ],
        "label": "background"
    },
    {
        "box": [
            228,
            183,
            272,
            199
        ],
        "label": "background"
    },
    {
        "box": [
            289,
            165,
            320,
            180
        ],
        "label": "background"
    },
    {
        "box": [
            68,
            248,
            95,
            256
        ],
        "label": "background"
    },
    {
        "box": [
            135,
            136,
            161,
            148
        ],
        "label": "background"
    },
    {
        "box": [
            328,
            95,
            387,
            125
        ],
        "label": "background"
    },
    {
        "box": [
            96,
            265,
            177,
            300
        ],
        "label": "pothole"
    },
    {
        "box": [
            4,
            0,
            398,
            177
        ],
        "label": "background"
    },
    {
        "box": [
            136,
            113,
            180,
            147
        ],
        "label": "background"
    },
    {
        "box": [
            239,
            91,
            265,
            101
        ],
        "label": "background"
    },
    {
        "box": [
            148,
            134,
            216,
            174
        ],
        "label": "background"
    },
    {
        "box": [
            179,
            43,
            398,
            154
        ],
        "label": "background"
    },
    {
        "box": [
            92,
            263,
            359,
            300
        ],
        "label": "background"
    },
    {
        "box": [
            307,
            124,
            346,
            154
        ],
        "label": "background"
    },
    {
        "box": [
            0,
            113,
            400,
            300
        ],
        "label": "background"
    },
    {
        "box": [
            4,
            273,
            15,
            300
        ],
        "label": "background"
    },
    {
        "box": [
            99,
            235,
            132,
            248
        ],
        "label": "background"
    },
    {
        "box": [
            193,
            168,
            270,
            200
        ],
        "label": "background"
    },
    {
        "box": [
            235,
            83,
            398,
            144
        ],
        "label": "background"
    },
    {
        "box": [
            76,
            141,
            174,
            178
        ],
        "label": "background"
    },
    {
        "box": [
            362,
            47,
            390,
            67
        ],
        "label": "background"
    },
    {
        "box": [
            0,
            223,
            64,
            272
        ],
        "label": "background"
    },
    {
        "box": [
            16,
            264,
            214,
            300
        ],
        "label": "background"
    },
    {
        "box": [
            0,
            0,
            11,
            24
        ],
        "label": "background"
    },
    {
        "box": [
            0,
            28,
            5,
            224
        ],
        "label": "background"
    },
    {
        "box": [
            5,
            171,
            112,
            231
        ],
        "label": "background"
    },
    {
        "box": [
            5,
            123,
            103,
            175
        ],
        "label": "background"
    },
    {
        "box": [
            235,
            95,
            284,
            107
        ],
        "label": "background"
    },
    {
        "box": [
            154,
            188,
            173,
            199
        ],
        "label": "background"
    },
    {
        "box": [
            121,
            297,
            356,
            300
        ],
        "label": "background"
    },
    {
        "box": [
            5,
            78,
            35,
            155
        ],
        "label": "background"
    },
    {
        "box": [
            128,
            31,
            156,
            43
        ],
        "label": "background"
    },
    {
        "box": [
            5,
            144,
            24,
            171
        ],
        "label": "background"
    },
    {
        "box": [
            5,
            78,
            35,
            192
        ],
        "label": "background"
    },
    {
        "box": [
            0,
            0,
            184,
            82
        ],
        "label": "background"
    },
    {
        "box": [
            287,
            124,
            339,
            155
        ],
        "label": "background"
    },
    {
        "box": [
            0,
            144,
            188,
            300
        ],
        "label": "background"
    },
    {
        "box": [
            5,
            80,
            35,
            155
        ],
        "label": "background"
    },
    {
        "box": [
            225,
            231,
            246,
            247
        ],
        "label": "background"
    },
    {
        "box": [
            138,
            87,
            166,
            99
        ],
        "label": "background"
    },
    {
        "box": [
            175,
            170,
            213,
            190
        ],
        "label": "background"
    },
    {
        "box": [
            95,
            265,
            359,
            300
        ],
        "label": "background"
    },
    {
        "box": [
            152,
            71,
            178,
            82
        ],
        "label": "background"
    },
    {
        "box": [
            328,
            115,
            368,
            137
        ],
        "label": "background"
    },
    {
        "box": [
            309,
            105,
            351,
            126
        ],
        "label": "background"
    },
    {
        "box": [
            388,
            0,
            398,
            104
        ],
        "label": "background"
    },
    {
        "box": [
            244,
            203,
            268,
            211
        ],
        "label": "background"
    },
    {
        "box": [
            340,
            0,
            400,
            300
        ],
        "label": "background"
    },
    {
        "box": [
            234,
            83,
            328,
            112
        ],
        "label": "pothole"
    },
    {
        "box": [
            115,
            269,
            147,
            285
        ],
        "label": "background"
    },
    {
        "box": [
            140,
            298,
            359,
            300
        ],
        "label": "background"
    },
    {
        "box": [
            5,
            0,
            39,
            20
        ],
        "label": "background"
    },
    {
        "box": [
            4,
            172,
            107,
            300
        ],
        "label": "background"
    },
    {
        "box": [
            0,
            64,
            4,
            208
        ],
        "label": "background"
    },
    {
        "box": [
            16,
            272,
            122,
            300
        ],
        "label": "background"
    },
    {
        "box": [
            70,
            266,
            92,
            285
        ],
        "label": "background"
    },
    {
        "box": [
            344,
            49,
            370,
            65
        ],
        "label": "background"
    },
    {
        "box": [
            121,
            272,
            214,
            300
        ],
        "label": "background"
    },
    {
        "box": [
            122,
            296,
            359,
            299
        ],
        "label": "background"
    },
    {
        "box": [
            328,
            95,
            391,
            134
        ],
        "label": "background"
    },
    {
        "box": [
            48,
            72,
            122,
            89
        ],
        "label": "background"
    },
    {
        "box": [
            345,
            50,
            370,
            63
        ],
        "label": "background"
    },
    {
        "box": [
            207,
            92,
            244,
            111
        ],
        "label": "background"
    },
    {
        "box": [
            44,
            263,
            91,
            289
        ],
        "label": "pothole"
    },
    {
        "box": [
            381,
            225,
            394,
            240
        ],
        "label": "background"
    },
    {
        "box": [
            289,
            164,
            320,
            182
        ],
        "label": "background"
    },
    {
        "box": [
            140,
            299,
            335,
            300
        ],
        "label": "background"
    },
    {
        "box": [
            0,
            160,
            3,
            300
        ],
        "label": "background"
    },
    {
        "box": [
            4,
            272,
            16,
            300
        ],
        "label": "background"
    },
    {
        "box": [
            242,
            48,
            397,
            100
        ],
        "label": "background"
    },
    {
        "box": [
            5,
            228,
            86,
            291
        ],
        "label": "background"
    },
    {
        "box": [
            331,
            98,
            384,
            126
        ],
        "label": "background"
    },
    {
        "box": [
            225,
            231,
            255,
            247
        ],
        "label": "background"
    },
    {
        "box": [
            60,
            145,
            82,
            154
        ],
        "label": "background"
    },
    {
        "box": [
            66,
            118,
            249,
            215
        ],
        "label": "pothole"
    },
    {
        "box": [
            398,
            0,
            400,
            178
        ],
        "label": "background"
    },
    {
        "box": [
            297,
            194,
            330,
            209
        ],
        "label": "background"
    },
    {
        "box": [
            68,
            140,
            266,
            233
        ],
        "label": "pothole"
    },
    {
        "box": [
            336,
            0,
            397,
            55
        ],
        "label": "background"
    },
    {
        "box": [
            139,
            202,
            203,
            226
        ],
        "label": "background"
    },
    {
        "box": [
            237,
            210,
            281,
            221
        ],
        "label": "background"
    },
    {
        "box": [
            5,
            184,
            95,
            298
        ],
        "label": "background"
    },
    {
        "box": [
            3,
            79,
            4,
            300
        ],
        "label": "background"
    },
    {
        "box": [
            5,
            109,
            398,
            300
        ],
        "label": "background"
    },
    {
        "box": [
            47,
            231,
            61,
            243
        ],
        "label": "background"
    },
    {
        "box": [
            121,
            299,
            356,
            300
        ],
        "label": "background"
    },
    {
        "box": [
            5,
            0,
            162,
            82
        ],
        "label": "background"
    },
    {
        "box": [
            16,
            275,
            121,
            300
        ],
        "label": "background"
    },
    {
        "box": [
            215,
            134,
            299,
            172
        ],
        "label": "background"
    },
    {
        "box": [
            143,
            64,
            208,
            81
        ],
        "label": "background"
    },
    {
        "box": [
            256,
            168,
            267,
            184
        ],
        "label": "background"
    },
    {
        "box": [
            289,
            164,
            304,
            181
        ],
        "label": "background"
    },
    {
        "box": [
            150,
            201,
            202,
            219
        ],
        "label": "background"
    },
    {
        "box": [
            336,
            0,
            368,
            55
        ],
        "label": "background"
    },
    {
        "box": [
            6,
            30,
            136,
            74
        ],
        "label": "background"
    },
    {
        "box": [
            390,
            0,
            398,
            104
        ],
        "label": "background"
    },
    {
        "box": [
            24,
            216,
            61,
            243
        ],
        "label": "background"
    },
    {
        "box": [
            62,
            137,
            83,
            150
        ],
        "label": "background"
    },
    {
        "box": [
            154,
            188,
            173,
            195
        ],
        "label": "background"
    },
    {
        "box": [
            0,
            0,
            48,
            69
        ],
        "label": "background"
    },
    {
        "box": [
            398,
            0,
            400,
            148
        ],
        "label": "background"
    },
    {
        "box": [
            40,
            250,
            91,
            293
        ],
        "label": "pothole"
    },
    {
        "box": [
            342,
            96,
            398,
            128
        ],
        "label": "background"
    },
    {
        "box": [
            195,
            191,
            297,
            218
        ],
        "label": "background"
    },
    {
        "box": [
            128,
            142,
            398,
            298
        ],
        "label": "background"
    },
    {
        "box": [
            364,
            162,
            394,
            177
        ],
        "label": "background"
    },
    {
        "box": [
            44,
            207,
            102,
            242
        ],
        "label": "background"
    },
    {
        "box": [
            179,
            85,
            244,
            111
        ],
        "label": "background"
    },
    {
        "box": [
            307,
            142,
            329,
            154
        ],
        "label": "background"
    },
    {
        "box": [
            101,
            264,
            181,
            300
        ],
        "label": "pothole"
    },
    {
        "box": [
            125,
            272,
            182,
            298
        ],
        "label": "background"
    },
    {
        "box": [
            206,
            140,
            258,
            164
        ],
        "label": "background"
    },
    {
        "box": [
            356,
            160,
            400,
            300
        ],
        "label": "background"
    },
    {
        "box": [
            163,
            202,
            204,
            226
        ],
        "label": "background"
    },
    {
        "box": [
            148,
            194,
            213,
            206
        ],
        "label": "background"
    },
    {
        "box": [
            5,
            111,
            120,
            242
        ],
        "label": "background"
    },
    {
        "box": [
            7,
            0,
            368,
            174
        ],
        "label": "background"
    },
    {
        "box": [
            55,
            140,
            272,
            226
        ],
        "label": "pothole"
    },
    {
        "box": [
            179,
            41,
            398,
            126
        ],
        "label": "background"
    },
    {
        "box": [
            106,
            255,
            131,
            273
        ],
        "label": "background"
    },
    {
        "box": [
            364,
            164,
            394,
            168
        ],
        "label": "background"
    },
    {
        "box": [
            0,
            170,
            214,
            300
        ],
        "label": "background"
    },
    {
        "box": [
            82,
            43,
            120,
            54
        ],
        "label": "background"
    },
    {
        "box": [
            399,
            0,
            400,
            104
        ],
        "label": "background"
    },
    {
        "box": [
            244,
            100,
            352,
            154
        ],
        "label": "background"
    },
    {
        "box": [
            289,
            165,
            322,
            180
        ],
        "label": "background"
    },
    {
        "box": [
            90,
            179,
            141,
            187
        ],
        "label": "background"
    },
    {
        "box": [
            215,
            134,
            289,
            165
        ],
        "label": "background"
    },
    {
        "box": [
            391,
            80,
            400,
            178
        ],
        "label": "background"
    },
    {
        "box": [
            307,
            109,
            399,
            163
        ],
        "label": "background"
    },
    {
        "box": [
            287,
            133,
            311,
            147
        ],
        "label": "background"
    },
    {
        "box": [
            254,
            100,
            344,
            142
        ],
        "label": "background"
    },
    {
        "box": [
            228,
            158,
            247,
            172
        ],
        "label": "background"
    },
    {
        "box": [
            398,
            0,
            399,
            104
        ],
        "label": "background"
    },
    {
        "box": [
            108,
            87,
            166,
            111
        ],
        "label": "background"
    },
    {
        "box": [
            101,
            264,
            182,
            300
        ],
        "label": "pothole"
    },
    {
        "box": [
            219,
            80,
            246,
            91
        ],
        "label": "background"
    },
    {
        "box": [
            10,
            0,
            48,
            32
        ],
        "label": "background"
    },
    {
        "box": [
            179,
            106,
            216,
            111
        ],
        "label": "background"
    },
    {
        "box": [
            55,
            140,
            267,
            216
        ],
        "label": "pothole"
    },
    {
        "box": [
            5,
            0,
            11,
            24
        ],
        "label": "background"
    },
    {
        "box": [
            383,
            160,
            398,
            206
        ],
        "label": "background"
    },
    {
        "box": [
            5,
            170,
            32,
            176
        ],
        "label": "background"
    },
    {
        "box": [
            5,
            170,
            113,
            299
        ],
        "label": "background"
    },
    {
        "box": [
            66,
            41,
            398,
            219
        ],
        "label": "background"
    },
    {
        "box": [
            5,
            36,
            282,
            192
        ],
        "label": "background"
    },
    {
        "box": [
            186,
            185,
            225,
            199
        ],
        "label": "background"
    },
    {
        "box": [
            119,
            35,
            156,
            46
        ],
        "label": "background"
    },
    {
        "box": [
            0,
            96,
            4,
            128
        ],
        "label": "background"
    },
    {
        "box": [
            225,
            186,
            270,
            199
        ],
        "label": "background"
    },
    {
        "box": [
            364,
            99,
            398,
            110
        ],
        "label": "background"
    },
    {
        "box": [
            289,
            165,
            308,
            182
        ],
        "label": "background"
    },
    {
        "box": [
            307,
            0,
            398,
            104
        ],
        "label": "background"
    },
    {
        "box": [
            336,
            0,
            390,
            67
        ],
        "label": "background"
    },
    {
        "box": [
            219,
            80,
            282,
            101
        ],
        "label": "background"
    },
    {
        "box": [
            148,
            161,
            272,
            206
        ],
        "label": "background"
    },
    {
        "box": [
            295,
            96,
            400,
            178
        ],
        "label": "background"
    },
    {
        "box": [
            119,
            27,
            184,
            46
        ],
        "label": "background"
    },
    {
        "box": [
            350,
            108,
            376,
            120
        ],
        "label": "background"
    },
    {
        "box": [
            312,
            64,
            371,
            79
        ],
        "label": "background"
    },
    {
        "box": [
            72,
            156,
            214,
            221
        ],
        "label": "pothole"
    },
    {
        "box": [
            5,
            185,
            113,
            299
        ],
        "label": "background"
    },
    {
        "box": [
            336,
            48,
            355,
            61
        ],
        "label": "background"
    },
    {
        "box": [
            91,
            113,
            216,
            178
        ],
        "label": "background"
    },
    {
        "box": [
            225,
            231,
            251,
            244
        ],
        "label": "background"
    },
    {
        "box": [
            215,
            116,
            352,
            181
        ],
        "label": "background"
    },
    {
        "box": [
            55,
            113,
            281,
            233
        ],
        "label": "background"
    },
    {
        "box": [
            101,
            203,
            176,
            221
        ],
        "label": "background"
    },
    {
        "box": [
            0,
            241,
            5,
            300
        ],
        "label": "background"
    },
    {
        "box": [
            5,
            168,
            32,
            182
        ],
        "label": "background"
    },
    {
        "box": [
            128,
            113,
            216,
            174
        ],
        "label": "background"
    },
    {
        "box": [
            340,
            178,
            400,
            300
        ],
        "label": "background"
    },
    {
        "box": [
            205,
            244,
            225,
            255
        ],
        "label": "background"
    },
    {
        "box": [
            340,
            159,
            400,
            300
        ],
        "label": "background"
    },
    {
        "box": [
            176,
            134,
            289,
            200
        ],
        "label": "background"
    },
    {
        "box": [
            244,
            100,
            352,
            144
        ],
        "label": "background"
    },
    {
        "box": [
            5,
            223,
            75,
            298
        ],
        "label": "background"
    },
    {
        "box": [
            5,
            34,
            80,
            74
        ],
        "label": "background"
    },
    {
        "box": [
            0,
            0,
            48,
            32
        ],
        "label": "background"
    },
    {
        "box": [
            55,
            169,
            93,
            181
        ],
        "label": "background"
    },
    {
        "box": [
            254,
            95,
            387,
            142
        ],
        "label": "background"
    },
    {
        "box": [
            3,
            0,
            12,
            24
        ],
        "label": "background"
    },
    {
        "box": [
            294,
            70,
            322,
            81
        ],
        "label": "background"
    },
    {
        "box": [
            361,
            0,
            397,
            48
        ],
        "label": "background"
    },
    {
        "box": [
            32,
            217,
            67,
            235
        ],
        "label": "background"
    },
    {
        "box": [
            307,
            144,
            337,
            154
        ],
        "label": "background"
    },
    {
        "box": [
            183,
            82,
            220,
            107
        ],
        "label": "background"
    },
    {
        "box": [
            179,
            92,
            247,
            115
        ],
        "label": "background"
    },
    {
        "box": [
            151,
            27,
            184,
            37
        ],
        "label": "background"
    },
    {
        "box": [
            347,
            119,
            376,
            127
        ],
        "label": "background"
    },
    {
        "box": [
            296,
            195,
            331,
            209
        ],
        "label": "background"
    },
    {
        "box": [
            228,
            211,
            281,
            228
        ],
        "label": "background"
    },
    {
        "box": [
            0,
            223,
            97,
            298
        ],
        "label": "background"
    },
    {
        "box": [
            179,
            83,
            398,
            144
        ],
        "label": "background"
    },
    {
        "box": [
            43,
            263,
            90,
            296
        ],
        "label": "pothole"
    },
    {
        "box": [
            179,
            89,
            245,
            110
        ],
        "label": "background"
    },
    {
        "box": [
            4,
            0,
            399,
            300
        ],
        "label": "background"
    },
    {
        "box": [
            215,
            95,
            387,
            172
        ],
        "label": "background"
    },
    {
        "box": [
            55,
            156,
            214,
            221
        ],
        "label": "pothole"
    },
    {
        "box": [
            148,
            191,
            297,
            218
        ],
        "label": "background"
    },
    {
        "box": [
            154,
            185,
            179,
            199
        ],
        "label": "background"
    },
    {
        "box": [
            350,
            99,
            398,
            120
        ],
        "label": "background"
    },
    {
        "box": [
            261,
            96,
            284,
            107
        ],
        "label": "background"
    },
    {
        "box": [
            179,
            89,
            244,
            115
        ],
        "label": "background"
    },
    {
        "box": [
            0,
            216,
            97,
            298
        ],
        "label": "background"
    },
    {
        "box": [
            140,
            298,
            340,
            300
        ],
        "label": "background"
    },
    {
        "box": [
            5,
            289,
            22,
            298
        ],
        "label": "background"
    },
    {
        "box": [
            10,
            0,
            281,
            47
        ],
        "label": "background"
    },
    {
        "box": [
            4,
            168,
            110,
            300
        ],
        "label": "background"
    },
    {
        "box": [
            121,
            299,
            359,
            300
        ],
        "label": "background"
    },
    {
        "box": [
            202,
            92,
            244,
            110
        ],
        "label": "background"
    },
    {
        "box": [
            0,
            0,
            18,
            32
        ],
        "label": "background"
    },
    {
        "box": [
            193,
            158,
            270,
            200
        ],
        "label": "background"
    },
    {
        "box": [
            0,
            0,
            281,
            47
        ],
        "label": "background"
    },
    {
        "box": [
            189,
            196,
            240,
            223
        ],
        "label": "background"
    },
    {
        "box": [
            361,
            159,
            398,
            232
        ],
        "label": "background"
    },
    {
        "box": [
            179,
            92,
            244,
            111
        ],
        "label": "background"
    },
    {
        "box": [
            328,
            109,
            399,
            163
        ],
        "label": "background"
    },
    {
        "box": [
            206,
            117,
            320,
            164
        ],
        "label": "background"
    },
    {
        "box": [
            319,
            98,
            354,
            112
        ],
        "label": "background"
    },
    {
        "box": [
            317,
            93,
            398,
            128
        ],
        "label": "background"
    },
    {
        "box": [
            179,
            106,
            215,
            111
        ],
        "label": "background"
    },
    {
        "box": [
            235,
            210,
            281,
            228
        ],
        "label": "background"
    },
    {
        "box": [
            271,
            134,
            289,
            147
        ],
        "label": "background"
    },
    {
        "box": [
            398,
            104,
            400,
            160
        ],
        "label": "background"
    },
    {
        "box": [
            143,
            71,
            178,
            83
        ],
        "label": "background"
    },
    {
        "box": [
            76,
            144,
            174,
            178
        ],
        "label": "background"
    },
    {
        "box": [
            278,
            210,
            303,
            226
        ],
        "label": "background"
    },
    {
        "box": [
            55,
            119,
            267,
            226
        ],
        "label": "background"
    },
    {
        "box": [
            121,
            297,
            356,
            299
        ],
        "label": "background"
    },
    {
        "box": [
            211,
            244,
            225,
            255
        ],
        "label": "background"
    },
    {
        "box": [
            285,
            100,
            329,
            114
        ],
        "label": "background"
    },
    {
        "box": [
            5,
            229,
            74,
            298
        ],
        "label": "background"
    },
    {
        "box": [
            0,
            223,
            177,
            300
        ],
        "label": "background"
    },
    {
        "box": [
            200,
            245,
            225,
            255
        ],
        "label": "background"
    },
    {
        "box": [
            69,
            249,
            87,
            266
        ],
        "label": "background"
    },
    {
        "box": [
            179,
            80,
            391,
            154
        ],
        "label": "background"
    },
    {
        "box": [
            225,
            185,
            272,
            199
        ],
        "label": "background"
    },
    {
        "box": [
            361,
            159,
            398,
            240
        ],
        "label": "background"
    },
    {
        "box": [
            152,
            76,
            208,
            82
        ],
        "label": "background"
    },
    {
        "box": [
            123,
            0,
            281,
            37
        ],
        "label": "background"
    },
    {
        "box": [
            40,
            263,
            91,
            293
        ],
        "label": "pothole"
    },
    {
        "box": [
            317,
            93,
            372,
            126
        ],
        "label": "background"
    },
    {
        "box": [
            215,
            116,
            352,
            166
        ],
        "label": "background"
    },
    {
        "box": [
            55,
            83,
            398,
            226
        ],
        "label": "background"
    },
    {
        "box": [
            131,
            36,
            160,
            42
        ],
        "label": "background"
    },
    {
        "box": [
            5,
            36,
            118,
            81
        ],
        "label": "background"
    },
    {
        "box": [
            179,
            48,
            398,
            206
        ],
        "label": "background"
    },
    {
        "box": [
            4,
            172,
            110,
            300
        ],
        "label": "background"
    },
    {
        "box": [
            307,
            109,
            399,
            206
        ],
        "label": "background"
    },
    {
        "box": [
            0,
            0,
            4,
            300
        ],
        "label": "background"
    },
    {
        "box": [
            234,
            83,
            325,
            112
        ],
        "label": "pothole"
    },
    {
        "box": [
            298,
            196,
            330,
            209
        ],
        "label": "background"
    },
    {
        "box": [
            243,
            213,
            279,
            224
        ],
        "label": "background"
    },
    {
        "box": [
            25,
            275,
            113,
            299
        ],
        "label": "background"
    },
    {
        "box": [
            295,
            112,
            400,
            178
        ],
        "label": "background"
    },
    {
        "box": [
            90,
            111,
            120,
            127
        ],
        "label": "background"
    },
    {
        "box": [
            5,
            111,
            230,
            242
        ],
        "label": "background"
    },
    {
        "box": [
            5,
            229,
            182,
            300
        ],
        "label": "background"
    },
    {
        "box": [
            208,
            195,
            237,
            205
        ],
        "label": "background"
    },
    {
        "box": [
            189,
            191,
            297,
            223
        ],
        "label": "background"
    },
    {
        "box": [
            226,
            187,
            267,
            195
        ],
        "label": "background"
    },
    {
        "box": [
            0,
            170,
            188,
            298
        ],
        "label": "background"
    },
    {
        "box": [
            309,
            98,
            384,
            126
        ],
        "label": "background"
    },
    {
        "box": [
            200,
            231,
            255,
            255
        ],
        "label": "background"
    },
    {
        "box": [
            179,
            83,
            398,
            166
        ],
        "label": "background"
    },
    {
        "box": [
            67,
            248,
            95,
            262
        ],
        "label": "background"
    },
    {
        "box": [
            0,
            240,
            4,
            272
        ],
        "label": "background"
    },
    {
        "box": [
            5,
            25,
            48,
            69
        ],
        "label": "background"
    },
    {
        "box": [
            55,
            170,
            83,
            181
        ],
        "label": "background"
    },
    {
        "box": [
            11,
            8,
            32,
            20
        ],
        "label": "background"
    },
    {
        "box": [
            138,
            87,
            152,
            99
        ],
        "label": "background"
    },
    {
        "box": [
            235,
            217,
            259,
            228
        ],
        "label": "background"
    },
    {
        "box": [
            0,
            0,
            107,
            300
        ],
        "label": "background"
    },
    {
        "box": [
            0,
            0,
            400,
            300
        ],
        "label": "background"
    },
    {
        "box": [
            317,
            93,
            384,
            126
        ],
        "label": "background"
    },
    {
        "box": [
            254,
            117,
            339,
            155
        ],
        "label": "background"
    },
    {
        "box": [
            335,
            178,
            400,
            300
        ],
        "label": "background"
    },
    {
        "box": [
            6,
            36,
            136,
            74
        ],
        "label": "background"
    },
    {
        "box": [
            292,
            43,
            397,
            104
        ],
        "label": "background"
    },
    {
        "box": [
            326,
            121,
            375,
            129
        ],
        "label": "background"
    },
    {
        "box": [
            223,
            139,
            276,
            165
        ],
        "label": "background"
    },
    {
        "box": [
            360,
            104,
            399,
            168
        ],
        "label": "background"
    },
    {
        "box": [
            20,
            216,
            65,
            233
        ],
        "label": "background"
    },
    {
        "box": [
            5,
            229,
            113,
            299
        ],
        "label": "background"
    },
    {
        "box": [
            350,
            108,
            384,
            123
        ],
        "label": "background"
    },
    {
        "box": [
            101,
            196,
            240,
            223
        ],
        "label": "background"
    },
    {
        "box": [
            43,
            262,
            92,
            285
        ],
        "label": "pothole"
    },
    {
        "box": [
            262,
            108,
            320,
            129
        ],
        "label": "background"
    },
    {
        "box": [
            219,
            80,
            282,
            95
        ],
        "label": "background"
    },
    {
        "box": [
            5,
            36,
            28,
            75
        ],
        "label": "background"
    },
    {
        "box": [
            46,
            170,
            83,
            181
        ],
        "label": "background"
    },
    {
        "box": [
            128,
            22,
            149,
            31
        ],
        "label": "background"
    },
    {
        "box": [
            4,
            240,
            122,
            300
        ],
        "label": "background"
    },
    {
        "box": [
            0,
            0,
            32,
            240
        ],
        "label": "background"
    },
    {
        "box": [
            55,
            43,
            398,
            226
        ],
        "label": "background"
    },
    {
        "box": [
            112,
            87,
            166,
            111
        ],
        "label": "background"
    },
    {
        "box": [
            0,
            113,
            281,
            300
        ],
        "label": "background"
    },
    {
        "box": [
            55,
            115,
            230,
            212
        ],
        "label": "background"
    },
    {
        "box": [
            223,
            134,
            302,
            172
        ],
        "label": "background"
    },
    {
        "box": [
            330,
            157,
            393,
            168
        ],
        "label": "background"
    },
    {
        "box": [
            328,
            109,
            399,
            206
        ],
        "label": "background"
    },
    {
        "box": [
            0,
            128,
            4,
            192
        ],
        "label": "background"
    },
    {
        "box": [
            68,
            140,
            266,
            215
        ],
        "label": "pothole"
    },
    {
        "box": [
            0,
            217,
            214,
            300
        ],
        "label": "background"
    },
    {
        "box": [
            16,
            272,
            214,
            300
        ],
        "label": "background"
    },
    {
        "box": [
            66,
            22,
            104,
            27
        ],
        "label": "background"
    },
    {
        "box": [
            0,
            28,
            35,
            224
        ],
        "label": "background"
    },
    {
        "box": [
            5,
            171,
            112,
            242
        ],
        "label": "background"
    },
    {
        "box": [
            121,
            272,
            356,
            299
        ],
        "label": "background"
    },
    {
        "box": [
            5,
            170,
            112,
            242
        ],
        "label": "background"
    },
    {
        "box": [
            0,
            96,
            4,
            192
        ],
        "label": "background"
    },
    {
        "box": [
            362,
            47,
            397,
            67
        ],
        "label": "background"
    },
    {
        "box": [
            330,
            157,
            398,
            206
        ],
        "label": "background"
    },
    {
        "box": [
            4,
            0,
            398,
            300
        ],
        "label": "background"
    },
    {
        "box": [
            206,
            93,
            372,
            164
        ],
        "label": "background"
    },
    {
        "box": [
            285,
            98,
            354,
            114
        ],
        "label": "background"
    },
    {
        "box": [
            5,
            185,
            74,
            298
        ],
        "label": "background"
    },
    {
        "box": [
            55,
            143,
            230,
            212
        ],
        "label": "pothole"
    },
    {
        "box": [
            5,
            216,
            90,
            298
        ],
        "label": "background"
    },
    {
        "box": [
            0,
            113,
            398,
            300
        ],
        "label": "background"
    },
    {
        "box": [
            179,
            70,
            331,
            111
        ],
        "label": "background"
    },
    {
        "box": [
            125,
            27,
            184,
            42
        ],
        "label": "background"
    },
    {
        "box": [
            289,
            112,
            400,
            180
        ],
        "label": "background"
    },
    {
        "box": [
            5,
            80,
            35,
            173
        ],
        "label": "background"
    },
    {
        "box": [
            0,
            0,
            400,
            192
        ],
        "label": "background"
    },
    {
        "box": [
            176,
            134,
            289,
            205
        ],
        "label": "background"
    },
    {
        "box": [
            0,
            240,
            122,
            300
        ],
        "label": "background"
    },
    {
        "box": [
            55,
            48,
            398,
            233
        ],
        "label": "background"
    },
    {
        "box": [
            5,
            113,
            216,
            178
        ],
        "label": "background"
    },
    {
        "box": [
            5,
            223,
            90,
            298
        ],
        "label": "background"
    },
    {
        "box": [
            5,
            0,
            281,
            81
        ],
        "label": "background"
    },
    {
        "box": [
            4,
            228,
            86,
            300
        ],
        "label": "background"
    },
    {
        "box": [
            205,
            139,
            276,
            165
        ],
        "label": "background"
    },
    {
        "box": [
            55,
            119,
            272,
            226
        ],
        "label": "background"
    },
    {
        "box": [
            176,
            173,
            225,
            199
        ],
        "label": "background"
    },
    {
        "box": [
            5,
            0,
            184,
            82
        ],
        "label": "background"
    },
    {
        "box": [
            0,
            0,
            59,
            224
        ],
        "label": "background"
    },
    {
        "box": [
            68,
            140,
            271,
            215
        ],
        "label": "pothole"
    },
    {
        "box": [
            46,
            159,
            230,
            212
        ],
        "label": "pothole"
    },
    {
        "box": [
            215,
            95,
            387,
            181
        ],
        "label": "background"
    },
    {
        "box": [
            29,
            216,
            65,
            243
        ],
        "label": "background"
    },
    {
        "box": [
            5,
            30,
            80,
            74
        ],
        "label": "background"
    },
    {
        "box": [
            206,
            140,
            276,
            166
        ],
        "label": "background"
    },
    {
        "box": [
            240,
            48,
            398,
            182
        ],
        "label": "background"
    },
    {
        "box": [
            5,
            0,
            48,
            75
        ],
        "label": "background"
    },
    {
        "box": [
            219,
            43,
            398,
            112
        ],
        "label": "background"
    },
    {
        "box": [
            336,
            0,
            398,
            104
        ],
        "label": "background"
    },
    {
        "box": [
            55,
            156,
            272,
            221
        ],
        "label": "pothole"
    },
    {
        "box": [
            287,
            124,
            346,
            154
        ],
        "label": "background"
    },
    {
        "box": [
            7,
            67,
            282,
            181
        ],
        "label": "background"
    },
    {
        "box": [
            0,
            0,
            399,
            300
        ],
        "label": "background"
    },
    {
        "box": [
            101,
            202,
            202,
            221
        ],
        "label": "background"
    },
    {
        "box": [
            189,
            196,
            281,
            223
        ],
        "label": "background"
    },
    {
        "box": [
            5,
            0,
            400,
            181
        ],
        "label": "background"
    },
    {
        "box": [
            0,
            170,
            177,
            300
        ],
        "label": "background"
    },
    {
        "box": [
            242,
            48,
            400,
            178
        ],
        "label": "background"
    },
    {
        "box": [
            390,
            0,
            400,
            160
        ],
        "label": "background"
    },
    {
        "box": [
            0,
            0,
            184,
            224
        ],
        "label": "background"
    },
    {
        "box": [
            101,
            188,
            331,
            228
        ],
        "label": "background"
    },
    {
        "box": [
            5,
            228,
            214,
            300
        ],
        "label": "background"
    },
    {
        "box": [
            4,
            104,
            399,
            300
        ],
        "label": "background"
    },
    {
        "box": [
            215,
            134,
            289,
            166
        ],
        "label": "background"
    },
    {
        "box": [
            198,
            191,
            297,
            259
        ],
        "label": "background"
    },
    {
        "box": [
            91,
            136,
            174,
            178
        ],
        "label": "background"
    },
    {
        "box": [
            307,
            0,
            400,
            300
        ],
        "label": "background"
    },
    {
        "box": [
            25,
            262,
            113,
            299
        ],
        "label": "pothole"
    },
    {
        "box": [
            131,
            27,
            185,
            42
        ],
        "label": "background"
    },
    {
        "box": [
            335,
            0,
            400,
            300
        ],
        "label": "background"
    },
    {
        "box": [
            226,
            183,
            272,
            199
        ],
        "label": "background"
    },
    {
        "box": [
            5,
            0,
            160,
            81
        ],
        "label": "background"
    },
    {
        "box": [
            244,
            95,
            391,
            144
        ],
        "label": "background"
    },
    {
        "box": [
            0,
            241,
            16,
            300
        ],
        "label": "background"
    },
    {
        "box": [
            4,
            171,
            359,
            300
        ],
        "label": "background"
    },
    {
        "box": [
            336,
            0,
            397,
            61
        ],
        "label": "background"
    },
    {
        "box": [
            0,
            0,
            32,
            32
        ],
        "label": "background"
    },
    {
        "box": [
            347,
            99,
            398,
            127
        ],
        "label": "background"
    },
    {
        "box": [
            4,
            0,
            398,
            219
        ],
        "label": "background"
    },
    {
        "box": [
            219,
            41,
            398,
            126
        ],
        "label": "background"
    },
    {
        "box": [
            0,
            0,
            162,
            82
        ],
        "label": "background"
    },
    {
        "box": [
            0,
            83,
            398,
            300
        ],
        "label": "background"
    },
    {
        "box": [
            25,
            261,
            113,
            299
        ],
        "label": "pothole"
    },
    {
        "box": [
            46,
            113,
            230,
            212
        ],
        "label": "background"
    },
    {
        "box": [
            0,
            0,
            397,
            240
        ],
        "label": "background"
    },
    {
        "box": [
            198,
            204,
            281,
            259
        ],
        "label": "background"
    },
    {
        "box": [
            0,
            0,
            110,
            300
        ],
        "label": "background"
    },
    {
        "box": [
            292,
            59,
            398,
            110
        ],
        "label": "background"
    },
    {
        "box": [
            287,
            93,
            372,
            155
        ],
        "label": "background"
    },
    {
        "box": [
            215,
            48,
            398,
            182
        ],
        "label": "background"
    },
    {
        "box": [
            195,
            191,
            297,
            221
        ],
        "label": "background"
    },
    {
        "box": [
            68,
            140,
            281,
            233
        ],
        "label": "background"
    },
    {
        "box": [
            4,
            0,
            399,
            206
        ],
        "label": "background"
    },
    {
        "box": [
            128,
            142,
            398,
            300
        ],
        "label": "background"
    },
    {
        "box": [
            101,
            191,
            331,
            226
        ],
        "label": "background"
    },
    {
        "box": [
            390,
            0,
            399,
            104
        ],
        "label": "background"
    },
    {
        "box": [
            235,
            83,
            398,
            154
        ],
        "label": "background"
    },
    {
        "box": [
            101,
            202,
            204,
            226
        ],
        "label": "background"
    },
    {
        "box": [
            360,
            0,
            399,
            168
        ],
        "label": "background"
    },
    {
        "box": [
            179,
            80,
            282,
            111
        ],
        "label": "background"
    },
    {
        "box": [
            5,
            135,
            398,
            300
        ],
        "label": "background"
    },
    {
        "box": [
            5,
            170,
            112,
            231
        ],
        "label": "background"
    },
    {
        "box": [
            7,
            48,
            400,
            181
        ],
        "label": "background"
    },
    {
        "box": [
            4,
            0,
            398,
            226
        ],
        "label": "background"
    },
    {
        "box": [
            336,
            0,
            397,
            67
        ],
        "label": "background"
    },
    {
        "box": [
            16,
            262,
            214,
            300
        ],
        "label": "background"
    },
    {
        "box": [
            0,
            0,
            398,
            192
        ],
        "label": "background"
    },
    {
        "box": [
            198,
            218,
            255,
            259
        ],
        "label": "background"
    },
    {
        "box": [
            44,
            0,
            353,
            111
        ],
        "label": "background"
    },
    {
        "box": [
            0,
            144,
            188,
            298
        ],
        "label": "background"
    },
    {
        "box": [
            292,
            43,
            398,
            110
        ],
        "label": "background"
    },
    {
        "box": [
            101,
            134,
            331,
            228
        ],
        "label": "background"
    },
    {
        "box": [
            179,
            0,
            398,
            172
        ],
        "label": "background"
    },
    {
        "box": [
            285,
            43,
            398,
            114
        ],
        "label": "background"
    },
    {
        "box": [
            68,
            140,
            271,
            233
        ],
        "label": "background"
    },
    {
        "box": [
            203,
            98,
            398,
            164
        ],
        "label": "background"
    },
    {
        "box": [
            5,
            223,
            95,
            298
        ],
        "label": "background"
    },
    {
        "box": [
            128,
            0,
            400,
            300
        ],
        "label": "background"
    },
    {
        "box": [
            179,
            48,
            398,
            176
        ],
        "label": "background"
    },
    {
        "box": [
            0,
            0,
            398,
            300
        ],
        "label": "background"
    },
    {
        "box": [
            123,
            0,
            281,
            42
        ],
        "label": "background"
    },
    {
        "box": [
            3,
            0,
            48,
            75
        ],
        "label": "background"
    },
    {
        "box": [
            189,
            191,
            297,
            259
        ],
        "label": "background"
    },
    {
        "box": [
            179,
            83,
            398,
            154
        ],
        "label": "background"
    },
    {
        "box": [
            5,
            123,
            112,
            242
        ],
        "label": "background"
    },
    {
        "box": [
            5,
            216,
            95,
            298
        ],
        "label": "background"
    },
    {
        "box": [
            7,
            64,
            282,
            178
        ],
        "label": "background"
    },
    {
        "box": [
            179,
            41,
            398,
            181
        ],
        "label": "background"
    },
    {
        "box": [
            179,
            0,
            400,
            300
        ],
        "label": "background"
    },
    {
        "box": [
            262,
            93,
            398,
            129
        ],
        "label": "background"
    },
    {
        "box": [
            101,
            194,
            213,
            226
        ],
        "label": "background"
    },
    {
        "box": [
            289,
            112,
            400,
            240
        ],
        "label": "background"
    },
    {
        "box": [
            187,
            117,
            320,
            200
        ],
        "label": "background"
    },
    {
        "box": [
            203,
            98,
            399,
            206
        ],
        "label": "background"
    },
    {
        "box": [
            0,
            240,
            177,
            300
        ],
        "label": "background"
    },
    {
        "box": [
            206,
            117,
            339,
            166
        ],
        "label": "background"
    },
    {
        "box": [
            179,
            48,
            400,
            178
        ],
        "label": "background"
    },
    {
        "box": [
            0,
            0,
            184,
            155
        ],
        "label": "background"
    },
    {
        "box": [
            55,
            115,
            276,
            226
        ],
        "label": "background"
    },
    {
        "box": [
            242,
            0,
            397,
            100
        ],
        "label": "background"
    },
    {
        "box": [
            143,
            134,
            398,
            300
        ],
        "label": "background"
    },
    {
        "box": [
            0,
            217,
            95,
            300
        ],
        "label": "background"
    },
    {
        "box": [
            148,
            158,
            272,
            206
        ],
        "label": "background"
    },
    {
        "box": [
            179,
            83,
            372,
            164
        ],
        "label": "background"
    },
    {
        "box": [
            72,
            156,
            240,
            223
        ],
        "label": "pothole"
    },
    {
        "box": [
            101,
            191,
            297,
            226
        ],
        "label": "background"
    },
    {
        "box": [
            0,
            0,
            368,
            174
        ],
        "label": "background"
    },
    {
        "box": [
            285,
            98,
            384,
            126
        ],
        "label": "background"
    },
    {
        "box": [
            47,
            83,
            398,
            298
        ],
        "label": "background"
    },
    {
        "box": [
            101,
            191,
            297,
            228
        ],
        "label": "background"
    },
    {
        "box": [
            55,
            115,
            270,
            226
        ],
        "label": "background"
    },
    {
        "box": [
            0,
            0,
            398,
            104
        ],
        "label": "background"
    },
    {
        "box": [
            5,
            159,
            331,
            299
        ],
        "label": "background"
    },
    {
        "box": [
            179,
            43,
            399,
            206
        ],
        "label": "background"
    },
    {
        "box": [
            72,
            156,
            270,
            223
        ],
        "label": "pothole"
    },
    {
        "box": [
            0,
            113,
            297,
            300
        ],
        "label": "background"
    },
    {
        "box": [
            187,
            158,
            270,
            200
        ],
        "label": "background"
    },
    {
        "box": [
            285,
            98,
            398,
            127
        ],
        "label": "background"
    },
    {
        "box": [
            187,
            134,
            289,
            200
        ],
        "label": "background"
    },
    {
        "box": [
            5,
            0,
            353,
            111
        ],
        "label": "background"
    },
    {
        "box": [
            193,
            134,
            289,
            200
        ],
        "label": "background"
    },
    {
        "box": [
            55,
            156,
            297,
            259
        ],
        "label": "background"
    },
    {
        "box": [
            0,
            216,
            340,
            300
        ],
        "label": "background"
    },
    {
        "box": [
            4,
            168,
            359,
            300
        ],
        "label": "background"
    },
    {
        "box": [
            66,
            159,
            331,
            228
        ],
        "label": "pothole"
    },
    {
        "box": [
            336,
            0,
            400,
            148
        ],
        "label": "background"
    },
    {
        "box": [
            5,
            185,
            182,
            300
        ],
        "label": "background"
    },
    {
        "box": [
            72,
            113,
            297,
            259
        ],
        "label": "background"
    },
    {
        "box": [
            179,
            43,
            397,
            111
        ],
        "label": "background"
    },
    {
        "box": [
            72,
            113,
            270,
            223
        ],
        "label": "background"
    },
    {
        "box": [
            4,
            111,
            398,
            300
        ],
        "label": "background"
    },
    {
        "box": [
            0,
            0,
            353,
            100
        ],
        "label": "background"
    },
    {
        "box": [
            0,
            112,
            398,
            300
        ],
        "label": "background"
    },
    {
        "box": [
            242,
            0,
            398,
            104
        ],
        "label": "background"
    },
    {
        "box": [
            0,
            156,
            297,
            300
        ],
        "label": "background"
    },
    {
        "box": [
            0,
            0,
            398,
            233
        ],
        "label": "background"
    },
    {
        "box": [
            285,
            43,
            399,
            206
        ],
        "label": "background"
    },
    {
        "box": [
            128,
            48,
            398,
            300
        ],
        "label": "background"
    },
    {
        "box": [
            5,
            111,
            216,
            178
        ],
        "label": "background"
    },
    {
        "box": [
            101,
            43,
            399,
            228
        ],
        "label": "background"
    },
    {
        "box": [
            5,
            159,
            356,
            300
        ],
        "label": "background"
    },
    {
        "box": [
            0,
            0,
            368,
            300
        ],
        "label": "background"
    },
    {
        "box": [
            4,
            172,
            182,
            300
        ],
        "label": "background"
    },
    {
        "box": [
            5,
            43,
            399,
            206
        ],
        "label": "background"
    },
    {
        "box": [
            187,
            98,
            384,
            200
        ],
        "label": "background"
    },
    {
        "box": [
            0,
            83,
            400,
            300
        ],
        "label": "background"
    },
    {
        "box": [
            4,
            0,
            399,
            228
        ],
        "label": "background"
    },
    {
        "box": [
            4,
            109,
            398,
            300
        ],
        "label": "background"
    },
    {
        "box": [
            4,
            0,
            400,
            300
        ],
        "label": "background"
    },
    {
        "box": [
            4,
            111,
            230,
            300
        ],
        "label": "background"
    },
    {
        "box": [
            179,
            83,
            400,
            240
        ],
        "label": "background"
    },
    {
        "box": [
            0,
            0,
            400,
            224
        ],
        "label": "background"
    }
]