[
    {
        "box": [
            371,
            301,
            400,
            311
        ],
        "label": "background",
        "max_iou": 0.0,
        "matched_gt": 0,
        "matches": []
    },
    {
        "box": [
            222,
            135,
            327,
            195
        ],
        "label": "background",
        "max_iou": 0.0,
        "matched_gt": 0,
        "matches": []
    },
    {
        "box": [
            290,
            338,
            315,
            357
        ],
        "label": "background",
        "max_iou": 0.0,
        "matched_gt": 0,
        "matches": []
    },
    {
        "box": [
            296,
            266,
            322,
            295
        ],
        "label": "background",
        "max_iou": 0.34873323397913564,
        "matched_gt": 2,
        "matches": []
    },
    {
        "box": [
            296,
            338,
            311,
            355
        ],
        "label": "background",
        "max_iou": 0.0,
        "matched_gt": 0,
        "matches": []
    },
    {
        "box": [
            349,
            159,
            400,
            183
        ],
        "label": "background",
        "max_iou": 0.0,
        "matched_gt": 0,
        "matches": []
    },
    {
        "box": [
            275,
            0,
            329,
            16
        ],
        "label": "background",
        "max_iou": 0.0,
        "matched_gt": 0,
        "matches": []
    },
    {
        "box": [
            166,
            121,
            227,
            137
        ],
        "label": "background",
        "max_iou": 0.022271102557052516,
        "matched_gt": 0,
        "matches": []
    },
    {
        "box": [
            97,
            201,
            116,
            217
        ],
        "label": "background",
        "max_iou": 0.0,
        "matched_gt": 0,
        "matches": []
    },
    {
        "box": [
            350,
            369,
            365,
            383
        ],
        "label": "background",
        "max_iou": 0.0,
        "matched_gt": 0,
        "matches": []
    },
    {
        "box": [
            93,
            129,
            272,
            360
        ],
        "label": "background",
        "max_iou": 0.2886435331230284,
        "matched_gt": 1,
        "matches": []
    },
    {
        "box": [
            141,
            130,
            182,
            187
        ],
        "label": "background",
        "max_iou": 0.36176470588235293,
        "matched_gt": 0,
        "matches": []
    },
    {
        "box": [
            0,
            347,
            12,
            374
        ],
        "label": "background",
        "max_iou": 0.0,
        "matched_gt": 0,
        "matches": []
    },
    {
        "box": [
            172,
            165,
            189,
            199
        ],
        "label": "background",
        "max_iou": 0.0558055805580558,
        "matched_gt": 0,
        "matches": []
    },
    {
        "box": [
            382,
            12,
            400,
            27
        ],
        "label": "background",
        "max_iou": 0.0,
        "matched_gt": 0,
        "matches": []
    },
    {
        "box": [
            249,
            161,
            293,
            186
        ],
        "label": "background",
        "max_iou": 0.0,
        "matched_gt": 0,
        "matches": []
    },
    {
        "box": [
            275,
            391,
            297,
            400
        ],
        "label": "background",
        "max_iou": 0.0,
        "matched_gt": 0,
        "matches": []
    },
    {
        "box": [
            168,
            134,
            284,
            227
        ],
        "label": "background",
        "max_iou": 0.11439202404236035,
        "matched_gt": 1,
        "matches": []
    },
    {
        "box": [
            304,
            310,
            319,
            330
        ],
        "label": "background",
        "max_iou": 0.0,
        "matched_gt": 0,
        "matches": []
    },
    {
        "box": [
            274,
            26,
            315,
            45
        ],
        "label": "background",
        "max_iou": 0.0,
        "matched_gt": 0,
        "matches": []
    },
    {
        "box": [
            106,
            61,
            146,
            79
        ],
        "label": "background",
        "max_iou": 0.0,
        "matched_gt": 0,
        "matches": []
    },
    {
        "box": [
            0,
            0,
            400,
            400
        ],
        "label": "background",
        "max_iou": 0.07858125,
        "matched_gt": 1,
        "matches": []
    },
    {
        "box": [
            237,
            327,
            258,
            341
        ],
        "label": "background",
        "max_iou": 0.0,
        "matched_gt": 0,
        "matches": []
    },
    {
        "box": [
            14,
            38,
            35,
            51
        ],
        "label": "background",
        "max_iou": 0.0,
        "matched_gt": 0,
        "matches": []
    },
    {
        "box": [
            247,
            274,
            270,
            299
        ],
        "label": "background",
        "max_iou": 0.04573291974866778,
        "matched_gt": 1,
        "matches": []
    },
    {
        "box": [
            168,
            116,
            190,
            125
        ],
        "label": "background",
        "max_iou": 0.0,
        "matched_gt": 0,
        "matches": []
    },
    {
        "box": [
            0,
            290,
            50,
            344
        ],
        "label": "background",
        "max_iou": 0.0,
        "matched_gt": 0,
        "matches": []
    },
    {
        "box": [
            181,
            205,
            241,
            232
        ],
        "label": "background",
        "max_iou": 0.12884753042233357,
        "matched_gt": 1,
        "matches": []
    },
    {
        "box": [
            142,
            75,
            223,
            136
        ],
        "label": "background",
        "max_iou": 0.03036601897876186,
        "matched_gt": 0,
        "matches": []
    },
    {
        "box": [
            312,
            339,
            342,
            356
        ],
        "label": "background",
        "max_iou": 0.0,
        "matched_gt": 0,
        "matches": []
    },
    {
        "box": [
            59,
            361,
            84,
            400
        ],
        "label": "background",
        "max_iou": 0.0,
        "matched_gt": 0,
        "matches": []
    },
    {
        "box": [
            284,
            0,
            400,
            26
        ],
        "label": "background",
        "max_iou": 0.0,
        "matched_gt": 0,
        "matches": []
    },
    {
        "box": [
            267,
            0,
            400,
            26
        ],
        "label": "background",
        "max_iou": 0.0,
        "matched_gt": 0,
        "matches": []
    },
    {
        "box": [
            246,
            178,
            328,
            260
        ],
        "label": "background",
        "max_iou": 0.09691905411550705,
        "matched_gt": 1,
        "matches": []
    },
    {
        "box": [
            357,
            387,
            377,
            400
        ],
        "label": "background",
        "max_iou": 0.0,
        "matched_gt": 0,
        "matches": []
    },
    {
        "box": [
            18,
            16,
            153,
            89
        ],
        "label": "background",
        "max_iou": 0.0,
        "matched_gt": 0,
        "matches": []
    },
    {
        "box": [
            176,
            115,
            221,
            132
        ],
        "label": "background",
        "max_iou": 0.0044487696371472265,
        "matched_gt": 0,
        "matches": []
    },
    {
        "box": [
            391,
            359,
            400,
            378
        ],
        "label": "background",
        "max_iou": 0.0,
        "matched_gt": 0,
        "matches": []
    },
    {
        "box": [
            247,
            278,
            267,
            299
        ],
        "label": "background",
        "max_iou": 0.03340491529467907,
        "matched_gt": 1,
        "matches": []
    },
    {
        "box": [
            185,
            107,
            216,
            117
        ],
        "label": "background",
        "max_iou": 0.0,
        "matched_gt": 0,
        "matches": []
    },
    {
        "box": [
            166,
            83,
            226,
            139
        ],
        "label": "background",
        "max_iou": 0.020577842444398253,
        "matched_gt": 0,
        "matches": []
    },
    {
        "box": [
            14,
            16,
            226,
            139
        ],
        "label": "background",
        "max_iou": 0.0331840843415579,
        "matched_gt": 0,
        "matches": []
    },
    {
        "box": [
            89,
            127,
            296,
            360
        ],
        "label": "background",
        "max_iou": 0.2606829632394103,
        "matched_gt": 1,
        "matches": []
    },
    {
        "box": [
            93,
            131,
            222,
            213
        ],
        "label": "pothole",
        "max_iou": 0.5317809943360604,
        "matched_gt": 0,
        "matches": [
            0
        ]
    },
    {
        "box": [
            0,
            347,
            30,
            400
        ],
        "label": "background",
        "max_iou": 0.0,
        "matched_gt": 0,
        "matches": []
    },
    {
        "box": [
            254,
            294,
            279,
            307
        ],
        "label": "background",
        "max_iou": 0.01815598358067572,
        "matched_gt": 1,
        "matches": []
    },
    {
        "box": [
            293,
            166,
            314,
            195
        ],
        "label": "background",
        "max_iou": 0.0,
        "matched_gt": 0,
        "matches": []
    },
    {
        "box": [
            161,
            123,
            312,
            227
        ],
        "label": "background",
        "max_iou": 0.09920310981535471,
        "matched_gt": 1,
        "matches": []
    },
    {
        "box": [
            155,
            134,
            177,
            166
        ],
        "label": "background",
        "max_iou": 0.10897832817337462,
        "matched_gt": 0,
        "matches": []
    },
    {
        "box": [
            26,
            290,
            49,
            307
        ],
        "label": "background",
        "max_iou": 0.0,
        "matched_gt": 0,
        "matches": []
    },
    {
        "box": [
            283,
            230,
            319,
            252
        ],
        "label": "background",
        "max_iou": 0.0,
        "matched_gt": 0,
        "matches": []
    },
    {
        "box": [
            93,
            130,
            222,
            213
        ],
        "label": "pothole",
        "max_iou": 0.5381238240301048,
        "matched_gt": 0,
        "matches": [
            0
        ]
    },
    {
        "box": [
            325,
            231,
            338,
            241
        ],
        "label": "background",
        "max_iou": 0.0,
        "matched_gt": 0,
        "matches": []
    },
    {
        "box": [
            189,
            107,
            208,
            116
        ],
        "label": "background",
        "max_iou": 0.0,
        "matched_gt": 0,
        "matches": []
    },
    {
        "box": [
            366,
            353,
            400,
            390
        ],
        "label": "background",
        "max_iou": 0.0,
        "matched_gt": 0,
        "matches": []
    },
    {
        "box": [
            64,
            208,
            95,
            248
        ],
        "label": "background",
        "max_iou": 0.0,
        "matched_gt": 0,
        "matches": []
    },
    {
        "box": [
            147,
            210,
            400,
            385
        ],
        "label": "background",
        "max_iou": 0.26582052994878647,
        "matched_gt": 1,
        "matches": []
    },
    {
        "box": [
            222,
            135,
            315,
            187
        ],
        "label": "background",
        "max_iou": 0.0,
        "matched_gt": 0,
        "matches": []
    },
    {
        "box": [
            363,
            328,
            385,
            341
        ],
        "label": "background",
        "max_iou": 0.0,
        "matched_gt": 0,
        "matches": []
    },
    {
        "box": [
            249,
            135,
            338,
            195
        ],
        "label": "background",
        "max_iou": 0.0,
        "matched_gt": 0,
        "matches": []
    },
    {
        "box": [
            329,
            80,
            346,
            89
        ],
        "label": "background",
        "max_iou": 0.0,
        "matched_gt": 0,
        "matches": []
    },
    {
        "box": [
            0,
            370,
            30,
            400
        ],
        "label": "background",
        "max_iou": 0.0,
        "matched_gt": 0,
        "matches": []
    },
    {
        "box": [
            118,
            118,
            153,
            142
        ],
        "label": "background",
        "max_iou": 0.07195301027900147,
        "matched_gt": 0,
        "matches": []
    },
    {
        "box": [
            141,
            133,
            163,
            152
        ],
        "label": "background",
        "max_iou": 0.06470588235294118,
        "matched_gt": 0,
        "matches": []
    },
    {
        "box": [
            195,
            0,
            400,
            63
        ],
        "label": "background",
        "max_iou": 0.0,
        "matched_gt": 0,
        "matches": []
    },
    {
        "box": [
            98,
            135,
            128,
            150
        ],
        "label": "background",
        "max_iou": 0.0696594427244582,
        "matched_gt": 0,
        "matches": []
    },
    {
        "box": [
            230,
            347,
            246,
            360
        ],
        "label": "background",
        "max_iou": 0.0,
        "matched_gt": 0,
        "matches": []
    },
    {
        "box": [
            0,
            310,
            17,
            344
        ],
        "label": "background",
        "max_iou": 0.0,
        "matched_gt": 0,
        "matches": []
    },
    {
        "box": [
            239,
            224,
            259,
            248
        ],
        "label": "background",
        "max_iou": 0.0381770460510618,
        "matched_gt": 1,
        "matches": []
    },
    {
        "box": [
            262,
            324,
            291,
            336
        ],
        "label": "background",
        "max_iou": 0.0,
        "matched_gt": 0,
        "matches": []
    },
    {
        "box": [
            181,
            205,
            218,
            222
        ],
        "label": "background",
        "max_iou": 0.050027837429412234,
        "matched_gt": 1,
        "matches": []
    },
    {
        "box": [
            206,
            295,
            272,
            358
        ],
        "label": "background",
        "max_iou": 0.03680981595092025,
        "matched_gt": 1,
        "matches": []
    },
    {
        "box": [
            314,
            218,
            347,
            243
        ],
        "label": "background",
        "max_iou": 0.0,
        "matched_gt": 0,
        "matches": []
    },
    {
        "box": [
            253,
            309,
            276,
            339
        ],
        "label": "background",
        "max_iou": 0.0,
        "matched_gt": 0,
        "matches": []
    },
    {
        "box": [
            328,
            107,
            346,
            118
        ],
        "label": "background",
        "max_iou": 0.0,
        "matched_gt": 0,
        "matches": []
    },
    {
        "box": [
            147,
            75,
            202,
            105
        ],
        "label": "background",
        "max_iou": 0.0,
        "matched_gt": 0,
        "matches": []
    },
    {
        "box": [
            352,
            70,
            392,
            92
        ],
        "label": "background",
        "max_iou": 0.0,
        "matched_gt": 0,
        "matches": []
    },
    {
        "box": [
            355,
            286,
            400,
            319
        ],
        "label": "background",
        "max_iou": 0.0,
        "matched_gt": 0,
        "matches": []
    },
    {
        "box": [
            336,
            107,
            391,
            135
        ],
        "label": "background",
        "max_iou": 0.0,
        "matched_gt": 0,
        "matches": []
    },
    {
        "box": [
            253,
            250,
            400,
            366
        ],
        "label": "background",
        "max_iou": 0.06192821956368754,
        "matched_gt": 2,
        "matches": []
    },
    {
        "box": [
            195,
            0,
            400,
            66
        ],
        "label": "background",
        "max_iou": 0.0,
        "matched_gt": 0,
        "matches": []
    },
    {
        "box": [
            214,
            301,
            235,
            315
        ],
        "label": "background",
        "max_iou": 0.0049203373945641985,
        "matched_gt": 1,
        "matches": []
    },
    {
        "box": [
            276,
            228,
            319,
            252
        ],
        "label": "background",
        "max_iou": 0.0017671747294013696,
        "matched_gt": 1,
        "matches": []
    },
    {
        "box": [
            230,
            345,
            246,
            360
        ],
        "label": "background",
        "max_iou": 0.0,
        "matched_gt": 0,
        "matches": []
    },
    {
        "box": [
            331,
            271,
            356,
            284
        ],
        "label": "background",
        "max_iou": 0.0,
        "matched_gt": 0,
        "matches": []
    },
    {
        "box": [
            75,
            62,
            100,
            74
        ],
        "label": "background",
        "max_iou": 0.0,
        "matched_gt": 0,
        "matches": []
    },
    {
        "box": [
            284,
            49,
            311,
            71
        ],
        "label": "background",
        "max_iou": 0.0,
        "matched_gt": 0,
        "matches": []
    },
    {
        "box": [
            155,
            134,
            242,
            222
        ],
        "label": "background",
        "max_iou": 0.14596525409969152,
        "matched_gt": 0,
        "matches": []
    },
    {
        "box": [
            299,
            266,
            321,
            281
        ],
        "label": "background",
        "max_iou": 0.06779661016949153,
        "matched_gt": 2,
        "matches": []
    },
    {
        "box": [
            18,
            290,
            50,
            303
        ],
        "label": "background",
        "max_iou": 0.0,
        "matched_gt": 0,
        "matches": []
    },
    {
        "box": [
            373,
            231,
            400,
            258
        ],
        "label": "background",
        "max_iou": 0.0,
        "matched_gt": 0,
        "matches": []
    },
    {
        "box": [
            267,
            240,
            400,
            400
        ],
        "label": "background",
        "max_iou": 0.04962406015037594,
        "matched_gt": 2,
        "matches": []
    },
    {
        "box": [
            89,
            127,
            400,
            385
        ],
        "label": "background",
        "max_iou": 0.15669632842294176,
        "matched_gt": 1,
        "matches": []
    },
    {
        "box": [
            209,
            209,
            240,
            230
        ],
        "label": "background",
        "max_iou": 0.051777618706752564,
        "matched_gt": 1,
        "matches": []
    },
    {
        "box": [
            51,
            362,
            81,
            400
        ],
        "label": "background",
        "max_iou": 0.0,
        "matched_gt": 0,
        "matches": []
    },
    {
        "box": [
            334,
            383,
            358,
            400
        ],
        "label": "background",
        "max_iou": 0.0,
        "matched_gt": 0,
        "matches": []
    },
    {
        "box": [
            357,
            72,
            381,
            88
        ],
        "label": "background",
        "max_iou": 0.0,
        "matched_gt": 0,
        "matches": []
    },
    {
        "box": [
            185,
            117,
            209,
            131
        ],
        "label": "background",
        "max_iou": 0.0,
        "matched_gt": 0,
        "matches": []
    },
    {
        "box": [
            0,
            360,
            31,
            400
        ],
        "label": "background",
        "max_iou": 0.0,
        "matched_gt": 0,
        "matches": []
    },
    {
        "box": [
            253,
            294,
            279,
            314
        ],
        "label": "background",
        "max_iou": 0.01867268342021318,
        "matched_gt": 1,
        "matches": []
    },
    {
        "box": [
            141,
            130,
            187,
            169
        ],
        "label": "background",
        "max_iou": 0.2549794739242816,
        "matched_gt": 0,
        "matches": []
    },
    {
        "box": [
            179,
            91,
            343,
            169
        ],
        "label": "background",
        "max_iou": 0.01076284979261826,
        "matched_gt": 0,
        "matches": []
    },
    {
        "box": [
            138,
            130,
            182,
            193
        ],
        "label": "background",
        "max_iou": 0.42910216718266253,
        "matched_gt": 0,
        "matches": []
    },
    {
        "box": [
            206,
            295,
            272,
            360
        ],
        "label": "background",
        "max_iou": 0.036511156186612576,
        "matched_gt": 1,
        "matches": []
    },
    {
        "box": [
            93,
            130,
            279,
            263
        ],
        "label": "background",
        "max_iou": 0.245984304558357,
        "matched_gt": 1,
        "matches": []
    },
    {
        "box": [
            0,
            0,
            400,
            172
        ],
        "label": "background",
        "max_iou": 0.05880697805289814,
        "matched_gt": 0,
        "matches": []
    },
    {
        "box": [
            10,
            291,
            26,
            319
        ],
        "label": "background",
        "max_iou": 0.0,
        "matched_gt": 0,
        "matches": []
    },
    {
        "box": [
            59,
            377,
            77,
            400
        ],
        "label": "background",
        "max_iou": 0.0,
        "matched_gt": 0,
        "matches": []
    },
    {
        "box": [
            314,
            216,
            347,
            232
        ],
        "label": "background",
        "max_iou": 0.0,
        "matched_gt": 0,
        "matches": []
    },
    {
        "box": [
            289,
            243,
            400,
            385
        ],
        "label": "background",
        "max_iou": 0.06699657403882756,
        "matched_gt": 2,
        "matches": []
    },
    {
        "box": [
            209,
            209,
            279,
            264
        ],
        "label": "background",
        "max_iou": 0.2948829141370338,
        "matched_gt": 1,
        "matches": []
    },
    {
        "box": [
            357,
            389,
            377,
            400
        ],
        "label": "background",
        "max_iou": 0.0,
        "matched_gt": 0,
        "matches": []
    },
    {
        "box": [
            284,
            0,
            313,
            16
        ],
        "label": "background",
        "max_iou": 0.0,
        "matched_gt": 0,
        "matches": []
    },
    {
        "box": [
            253,
            243,
            400,
            389
        ],
        "label": "background",
        "max_iou": 0.04920324294101202,
        "matched_gt": 2,
        "matches": []
    },
    {
        "box": [
            275,
            391,
            296,
            400
        ],
        "label": "background",
        "max_iou": 0.0,
        "matched_gt": 0,
        "matches": []
    },
    {
        "box": [
            107,
            229,
            126,
            246
        ],
        "label": "background",
        "max_iou": 0.0,
        "matched_gt": 0,
        "matches": []
    },
    {
        "box": [
            311,
            45,
            400,
            76
        ],
        "label": "background",
        "max_iou": 0.0,
        "matched_gt": 0,
        "matches": []
    },
    {
        "box": [
            307,
            161,
            327,
            172
        ],
        "label": "background",
        "max_iou": 0.0,
        "matched_gt": 0,
        "matches": []
    },
    {
        "box": [
            329,
            80,
            347,
            89
        ],
        "label": "background",
        "max_iou": 0.0,
        "matched_gt": 0,
        "matches": []
    },
    {
        "box": [
            290,
            164,
            307,
            179
        ],
        "label": "background",
        "max_iou": 0.0,
        "matched_gt": 0,
        "matches": []
    },
    {
        "box": [
            179,
            189,
            213,
            214
        ],
        "label": "background",
        "max_iou": 0.02332850499351986,
        "matched_gt": 1,
        "matches": []
    },
    {
        "box": [
            243,
            134,
            400,
            320
        ],
        "label": "background",
        "max_iou": 0.0876357103803796,
        "matched_gt": 1,
        "matches": []
    },
    {
        "box": [
            362,
            328,
            386,
            342
        ],
        "label": "background",
        "max_iou": 0.0,
        "matched_gt": 0,
        "matches": []
    },
    {
        "box": [
            298,
            338,
            327,
            366
        ],
        "label": "background",
        "max_iou": 0.0,
        "matched_gt": 0,
        "matches": []
    },
    {
        "box": [
            24,
            371,
            42,
            389
        ],
        "label": "background",
        "max_iou": 0.0,
        "matched_gt": 0,
        "matches": []
    },
    {
        "box": [
            284,
            0,
            326,
            15
        ],
        "label": "background",
        "max_iou": 0.0,
        "matched_gt": 0,
        "matches": []
    },
    {
        "box": [
            97,
            134,
            127,
            150
        ],
        "label": "background",
        "max_iou": 0.07430340557275542,
        "matched_gt": 0,
        "matches": []
    },
    {
        "box": [
            391,
            133,
            400,
            151
        ],
        "label": "background",
        "max_iou": 0.0,
        "matched_gt": 0,
        "matches": []
    },
    {
        "box": [
            145,
            149,
            182,
            187
        ],
        "label": "background",
        "max_iou": 0.21764705882352942,
        "matched_gt": 0,
        "matches": []
    },
    {
        "box": [
            0,
            37,
            342,
            400
        ],
        "label": "background",
        "max_iou": 0.10127591706539076,
        "matched_gt": 1,
        "matches": []
    },
    {
        "box": [
            0,
            360,
            42,
            400
        ],
        "label": "background",
        "max_iou": 0.0,
        "matched_gt": 0,
        "matches": []
    },
    {
        "box": [
            318,
            164,
            338,
            174
        ],
        "label": "background",
        "max_iou": 0.0,
        "matched_gt": 0,
        "matches": []
    },
    {
        "box": [
            12,
            333,
            93,
            400
        ],
        "label": "background",
        "max_iou": 0.0,
        "matched_gt": 0,
        "matches": []
    },
    {
        "box": [
            311,
            247,
            356,
            264
        ],
        "label": "background",
        "max_iou": 0.0,
        "matched_gt": 0,
        "matches": []
    },
    {
        "box": [
            204,
            0,
            386,
            51
        ],
        "label": "background",
        "max_iou": 0.0,
        "matched_gt": 0,
        "matches": []
    },
    {
        "box": [
            254,
            274,
            278,
            307
        ],
        "label": "background",
        "max_iou": 0.054437869822485205,
        "matched_gt": 1,
        "matches": []
    },
    {
        "box": [
            73,
            375,
            93,
            391
        ],
        "label": "background",
        "max_iou": 0.0,
        "matched_gt": 0,
        "matches": []
    },
    {
        "box": [
            235,
            232,
            282,
            289
        ],
        "label": "background",
        "max_iou": 0.18618758749416706,
        "matched_gt": 1,
        "matches": []
    },
    {
        "box": [
            369,
            349,
            400,
            373
        ],
        "label": "background",
        "max_iou": 0.0,
        "matched_gt": 0,
        "matches": []
    },
    {
        "box": [
            97,
            118,
            153,
            150
        ],
        "label": "background",
        "max_iou": 0.1754985754985755,
        "matched_gt": 0,
        "matches": []
    },
    {
        "box": [
            94,
            200,
            117,
            214
        ],
        "label": "background",
        "max_iou": 0.0,
        "matched_gt": 0,
        "matches": []
    },
    {
        "box": [
            269,
            141,
            326,
            170
        ],
        "label": "background",
        "max_iou": 0.0,
        "matched_gt": 0,
        "matches": []
    },
    {
        "box": [
            267,
            231,
            400,
            400
        ],
        "label": "background",
        "max_iou": 0.046981358722249414,
        "matched_gt": 2,
        "matches": []
    },
    {
        "box": [
            380,
            303,
            400,
            319
        ],
        "label": "background",
        "max_iou": 0.0,
        "matched_gt": 0,
        "matches": []
    },
    {
        "box": [
            27,
            290,
            49,
            304
        ],
        "label": "background",
        "max_iou": 0.0,
        "matched_gt": 0,
        "matches": []
    },
    {
        "box": [
            337,
            378,
            362,
            397
        ],
        "label": "background",
        "max_iou": 0.0,
        "matched_gt": 0,
        "matches": []
    },
    {
        "box": [
            169,
            83,
            221,
            116
        ],
        "label": "background",
        "max_iou": 0.0,
        "matched_gt": 0,
        "matches": []
    },
    {
        "box": [
            11,
            290,
            26,
            319
        ],
        "label": "background",
        "max_iou": 0.0,
        "matched_gt": 0,
        "matches": []
    },
    {
        "box": [
            267,
            0,
            285,
            9
        ],
        "label": "background",
        "max_iou": 0.0,
        "matched_gt": 0,
        "matches": []
    },
    {
        "box": [
            359,
            0,
            400,
            27
        ],
        "label": "background",
        "max_iou": 0.0,
        "matched_gt": 0,
        "matches": []
    },
    {
        "box": [
            240,
            149,
            258,
            160
        ],
        "label": "background",
        "max_iou": 0.0,
        "matched_gt": 0,
        "matches": []
    },
    {
        "box": [
            137,
            70,
            169,
            89
        ],
        "label": "background",
        "max_iou": 0.0,
        "matched_gt": 0,
        "matches": []
    },
    {
        "box": [
            311,
            45,
            400,
            88
        ],
        "label": "background",
        "max_iou": 0.0,
        "matched_gt": 0,
        "matches": []
    },
    {
        "box": [
            213,
            302,
            229,
            315
        ],
        "label": "background",
        "max_iou": 0.002510000784375245,
        "matched_gt": 1,
        "matches": []
    },
    {
        "box": [
            262,
            312,
            278,
            339
        ],
        "label": "background",
        "max_iou": 0.0,
        "matched_gt": 0,
        "matches": []
    },
    {
        "box": [
            178,
            203,
            196,
            215
        ],
        "label": "background",
        "max_iou": 0.014275517487508922,
        "matched_gt": 1,
        "matches": []
    },
    {
        "box": [
            312,
            38,
            328,
            50
        ],
        "label": "background",
        "max_iou": 0.0,
        "matched_gt": 0,
        "matches": []
    },
    {
        "box": [
            106,
            60,
            169,
            90
        ],
        "label": "background",
        "max_iou": 0.0,
        "matched_gt": 0,
        "matches": []
    },
    {
        "box": [
            352,
            307,
            369,
            321
        ],
        "label": "background",
        "max_iou": 0.0,
        "matched_gt": 0,
        "matches": []
    },
    {
        "box": [
            201,
            80,
            400,
            320
        ],
        "label": "background",
        "max_iou": 0.1424757143668693,
        "matched_gt": 1,
        "matches": []
    },
    {
        "box": [
            187,
            341,
            206,
            363
        ],
        "label": "background",
        "max_iou": 0.0,
        "matched_gt": 0,
        "matches": []
    },
    {
        "box": [
            253,
            247,
            400,
            366
        ],
        "label": "background",
        "max_iou": 0.060367003944434915,
        "matched_gt": 2,
        "matches": []
    },
    {
        "box": [
            241,
            223,
            259,
            248
        ],
        "label": "background",
        "max_iou": 0.03579098067287044,
        "matched_gt": 1,
        "matches": []
    },
    {
        "box": [
            11,
            290,
            50,
            317
        ],
        "label": "background",
        "max_iou": 0.0,
        "matched_gt": 0,
        "matches": []
    },
    {
        "box": [
            129,
            233,
            144,
            256
        ],
        "label": "background",
        "max_iou": 0.0,
        "matched_gt": 0,
        "matches": []
    },
    {
        "box": [
            307,
            3,
            330,
            15
        ],
        "label": "background",
        "max_iou": 0.0,
        "matched_gt": 0,
        "matches": []
    },
    {
        "box": [
            338,
            309,
            358,
            321
        ],
        "label": "background",
        "max_iou": 0.0,
        "matched_gt": 0,
        "matches": []
    },
    {
        "box": [
            0,
            347,
            49,
            400
        ],
        "label": "background",
        "max_iou": 0.0,
        "matched_gt": 0,
        "matches": []
    },
    {
        "box": [
            356,
            71,
            392,
            89
        ],
        "label": "background",
        "max_iou": 0.0,
        "matched_gt": 0,
        "matches": []
    },
    {
        "box": [
            51,
            361,
            82,
            400
        ],
        "label": "background",
        "max_iou": 0.0,
        "matched_gt": 0,
        "matches": []
    },
    {
        "box": [
            201,
            247,
            400,
            366
        ],
        "label": "background",
        "max_iou": 0.13570578284568635,
        "matched_gt": 1,
        "matches": []
    },
    {
        "box": [
            235,
            232,
            282,
            307
        ],
        "label": "background",
        "max_iou": 0.2312987608994952,
        "matched_gt": 1,
        "matches": []
    },
    {
        "box": [
            99,
            262,
            125,
            288
        ],
        "label": "background",
        "max_iou": 0.0,
        "matched_gt": 0,
        "matches": []
    },
    {
        "box": [
            62,
            361,
            84,
            382
        ],
        "label": "background",
        "max_iou": 0.0,
        "matched_gt": 0,
        "matches": []
    },
    {
        "box": [
            62,
            361,
            84,
            386
        ],
        "label": "background",
        "max_iou": 0.0,
        "matched_gt": 0,
        "matches": []
    },
    {
        "box": [
            272,
            141,
            327,
            172
        ],
        "label": "background",
        "max_iou": 0.0,
        "matched_gt": 0,
        "matches": []
    },
    {
        "box": [
            197,
            343,
            206,
            363
        ],
        "label": "background",
        "max_iou": 0.0,
        "matched_gt": 0,
        "matches": []
    },
    {
        "box": [
            293,
            62,
            311,
            71
        ],
        "label": "background",
        "max_iou": 0.0,
        "matched_gt": 0,
        "matches": []
    },
    {
        "box": [
            168,
            134,
            284,
            208
        ],
        "label": "background",
        "max_iou": 0.07059493310560774,
        "matched_gt": 0,
        "matches": []
    },
    {
        "box": [
            85,
            118,
            267,
            310
        ],
        "label": "background",
        "max_iou": 0.3223409584237769,
        "matched_gt": 1,
        "matches": []
    },
    {
        "box": [
            183,
            169,
            231,
            211
        ],
        "label": "background",
        "max_iou": 0.020138451856513532,
        "matched_gt": 1,
        "matches": []
    },
    {
        "box": [
            61,
            204,
            98,
            248
        ],
        "label": "background",
        "max_iou": 0.0,
        "matched_gt": 0,
        "matches": []
    },
    {
        "box": [
            147,
            75,
            198,
            105
        ],
        "label": "background",
        "max_iou": 0.0,
        "matched_gt": 0,
        "matches": []
    },
    {
        "box": [
            12,
            333,
            88,
            400
        ],
        "label": "background",
        "max_iou": 0.0,
        "matched_gt": 0,
        "matches": []
    },
    {
        "box": [
            97,
            135,
            128,
            150
        ],
        "label": "background",
        "max_iou": 0.07198142414860681,
        "matched_gt": 0,
        "matches": []
    },
    {
        "box": [
            365,
            355,
            388,
            375
        ],
        "label": "background",
        "max_iou": 0.0,
        "matched_gt": 0,
        "matches": []
    },
    {
        "box": [
            93,
            129,
            272,
            352
        ],
        "label": "background",
        "max_iou": 0.2988716222904088,
        "matched_gt": 1,
        "matches": []
    },
    {
        "box": [
            14,
            16,
            153,
            89
        ],
        "label": "background",
        "max_iou": 0.0,
        "matched_gt": 0,
        "matches": []
    },
    {
        "box": [
            158,
            141,
            187,
            157
        ],
        "label": "background",
        "max_iou": 0.06392132759680394,
        "matched_gt": 0,
        "matches": []
    },
    {
        "box": [
            155,
            143,
            187,
            156
        ],
        "label": "background",
        "max_iou": 0.05800892444991537,
        "matched_gt": 0,
        "matches": []
    },
    {
        "box": [
            138,
            142,
            181,
            187
        ],
        "label": "background",
        "max_iou": 0.2995356037151703,
        "matched_gt": 0,
        "matches": []
    },
    {
        "box": [
            0,
            333,
            93,
            400
        ],
        "label": "background",
        "max_iou": 0.0,
        "matched_gt": 0,
        "matches": []
    },
    {
        "box": [
            279,
            293,
            296,
            309
        ],
        "label": "background",
        "max_iou": 0.0641025641025641,
        "matched_gt": 2,
        "matches": []
    },
    {
        "box": [
            301,
            173,
            314,
            195
        ],
        "label": "background",
        "max_iou": 0.0,
        "matched_gt": 0,
        "matches": []
    },
    {
        "box": [
            10,
            290,
            26,
            319
        ],
        "label": "background",
        "max_iou": 0.0,
        "matched_gt": 0,
        "matches": []
    },
    {
        "box": [
            159,
            154,
            179,
            166
        ],
        "label": "background",
        "max_iou": 0.03715170278637771,
        "matched_gt": 0,
        "matches": []
    },
    {
        "box": [
            24,
            363,
            42,
            389
        ],
        "label": "background",
        "max_iou": 0.0,
        "matched_gt": 0,
        "matches": []
    },
    {
        "box": [
            139,
            55,
            162,
            66
        ],
        "label": "background",
        "max_iou": 0.0,
        "matched_gt": 0,
        "matches": []
    },
    {
        "box": [
            179,
            196,
            242,
            222
        ],
        "label": "background",
        "max_iou": 0.08150684931506849,
        "matched_gt": 1,
        "matches": []
    },
    {
        "box": [
            199,
            0,
            400,
            60
        ],
        "label": "background",
        "max_iou": 0.0,
        "matched_gt": 0,
        "matches": []
    },
    {
        "box": [
            247,
            242,
            282,
            289
        ],
        "label": "background",
        "max_iou": 0.11008744534665833,
        "matched_gt": 1,
        "matches": []
    },
    {
        "box": [
            363,
            286,
            383,
            295
        ],
        "label": "background",
        "max_iou": 0.0,
        "matched_gt": 0,
        "matches": []
    },
    {
        "box": [
            356,
            72,
            381,
            89
        ],
        "label": "background",
        "max_iou": 0.0,
        "matched_gt": 0,
        "matches": []
    },
    {
        "box": [
            206,
            294,
            279,
            358
        ],
        "label": "background",
        "max_iou": 0.04293921983671001,
        "matched_gt": 1,
        "matches": []
    },
    {
        "box": [
            209,
            209,
            241,
            232
        ],
        "label": "background",
        "max_iou": 0.05853813727829476,
        "matched_gt": 1,
        "matches": []
    },
    {
        "box": [
            18,
            341,
            36,
            351
        ],
        "label": "background",
        "max_iou": 0.0,
        "matched_gt": 0,
        "matches": []
    },
    {
        "box": [
            97,
            200,
            116,
            222
        ],
        "label": "background",
        "max_iou": 0.0,
        "matched_gt": 0,
        "matches": []
    },
    {
        "box": [
            93,
            129,
            400,
            389
        ],
        "label": "background",
        "max_iou": 0.15751691305437235,
        "matched_gt": 1,
        "matches": []
    },
    {
        "box": [
            328,
            107,
            347,
            120
        ],
        "label": "background",
        "max_iou": 0.0,
        "matched_gt": 0,
        "matches": []
    },
    {
        "box": [
            27,
            290,
            49,
            307
        ],
        "label": "background",
        "max_iou": 0.0,
        "matched_gt": 0,
        "matches": []
    },
    {
        "box": [
            85,
            127,
            400,
            366
        ],
        "label": "background",
        "max_iou": 0.1670053795576808,
        "matched_gt": 1,
        "matches": []
    },
    {
        "box": [
            179,
            189,
            277,
            298
        ],
        "label": "pothole",
        "max_iou": 0.644508874902765,
        "matched_gt": 1,
        "matches": [
            1
        ]
    },
    {
        "box": [
            373,
            76,
            400,
            88
        ],
        "label": "background",
        "max_iou": 0.0,
        "matched_gt": 0,
        "matches": []
    },
    {
        "box": [
            184,
            338,
            206,
            363
        ],
        "label": "background",
        "max_iou": 0.0,
        "matched_gt": 0,
        "matches": []
    },
    {
        "box": [
            0,
            166,
            24,
            182
        ],
        "label": "background",
        "max_iou": 0.0,
        "matched_gt": 0,
        "matches": []
    },
    {
        "box": [
            363,
            288,
            383,
            295
        ],
        "label": "background",
        "max_iou": 0.0,
        "matched_gt": 0,
        "matches": []
    },
    {
        "box": [
            196,
            148,
            213,
            160
        ],
        "label": "background",
        "max_iou": 0.0,
        "matched_gt": 0,
        "matches": []
    },
    {
        "box": [
            14,
            30,
            55,
            65
        ],
        "label": "background",
        "max_iou": 0.0,
        "matched_gt": 0,
        "matches": []
    },
    {
        "box": [
            85,
            127,
            400,
            390
        ],
        "label": "background",
        "max_iou": 0.15176534492123847,
        "matched_gt": 1,
        "matches": []
    },
    {
        "box": [
            311,
            132,
            338,
            146
        ],
        "label": "background",
        "max_iou": 0.0,
        "matched_gt": 0,
        "matches": []
    },
    {
        "box": [
            195,
            11,
            219,
            18
        ],
        "label": "background",
        "max_iou": 0.0,
        "matched_gt": 0,
        "matches": []
    },
    {
        "box": [
            294,
            63,
            311,
            71
        ],
        "label": "background",
        "max_iou": 0.0,
        "matched_gt": 0,
        "matches": []
    },
    {
        "box": [
            14,
            30,
            63,
            66
        ],
        "label": "background",
        "max_iou": 0.0,
        "matched_gt": 0,
        "matches": []
    },
    {
        "box": [
            161,
            113,
            315,
            227
        ],
        "label": "background",
        "max_iou": 0.09254088552054249,
        "matched_gt": 1,
        "matches": []
    },
    {
        "box": [
            208,
            196,
            275,
            227
        ],
        "label": "background",
        "max_iou": 0.11187006678809958,
        "matched_gt": 1,
        "matches": []
    },
    {
        "box": [
            55,
            342,
            80,
            358
        ],
        "label": "background",
        "max_iou": 0.0,
        "matched_gt": 0,
        "matches": []
    },
    {
        "box": [
            231,
            113,
            315,
            164
        ],
        "label": "background",
        "max_iou": 0.0,
        "matched_gt": 0,
        "matches": []
    },
    {
        "box": [
            185,
            117,
            223,
            132
        ],
        "label": "background",
        "max_iou": 0.0,
        "matched_gt": 0,
        "matches": []
    },
    {
        "box": [
            284,
            0,
            335,
            19
        ],
        "label": "background",
        "max_iou": 0.0,
        "matched_gt": 0,
        "matches": []
    },
    {
        "box": [
            146,
            137,
            163,
            151
        ],
        "label": "background",
        "max_iou": 0.03684210526315789,
        "matched_gt": 0,
        "matches": []
    },
    {
        "box": [
            334,
            369,
            383,
            400
        ],
        "label": "background",
        "max_iou": 0.0,
        "matched_gt": 0,
        "matches": []
    },
    {
        "box": [
            85,
            167,
            263,
            310
        ],
        "label": "background",
        "max_iou": 0.41680327868852457,
        "matched_gt": 1,
        "matches": []
    },
    {
        "box": [
            363,
            243,
            390,
            254
        ],
        "label": "background",
        "max_iou": 0.0,
        "matched_gt": 0,
        "matches": []
    },
    {
        "box": [
            0,
            0,
            400,
            250
        ],
        "label": "background",
        "max_iou": 0.0646,
        "matched_gt": 0,
        "matches": []
    },
    {
        "box": [
            141,
            130,
            163,
            152
        ],
        "label": "background",
        "max_iou": 0.07492260061919505,
        "matched_gt": 0,
        "matches": []
    },
    {
        "box": [
            317,
            340,
            342,
            356
        ],
        "label": "background",
        "max_iou": 0.0,
        "matched_gt": 0,
        "matches": []
    },
    {
        "box": [
            66,
            209,
            95,
            248
        ],
        "label": "background",
        "max_iou": 0.0,
        "matched_gt": 0,
        "matches": []
    },
    {
        "box": [
            290,
            164,
            316,
            196
        ],
        "label": "background",
        "max_iou": 0.0,
        "matched_gt": 0,
        "matches": []
    },
    {
        "box": [
            315,
            13,
            386,
            51
        ],
        "label": "background",
        "max_iou": 0.0,
        "matched_gt": 0,
        "matches": []
    },
    {
        "box": [
            85,
            167,
            267,
            310
        ],
        "label": "background",
        "max_iou": 0.42874592833876224,
        "matched_gt": 1,
        "matches": []
    },
    {
        "box": [
            215,
            367,
            228,
            381
        ],
        "label": "background",
        "max_iou": 0.0,
        "matched_gt": 0,
        "matches": []
    },
    {
        "box": [
            106,
            60,
            139,
            79
        ],
        "label": "background",
        "max_iou": 0.0,
        "matched_gt": 0,
        "matches": []
    },
    {
        "box": [
            74,
            157,
            95,
            176
        ],
        "label": "background",
        "max_iou": 0.016901408450704224,
        "matched_gt": 0,
        "matches": []
    },
    {
        "box": [
            0,
            17,
            373,
            400
        ],
        "label": "background",
        "max_iou": 0.08800985587187367,
        "matched_gt": 1,
        "matches": []
    },
    {
        "box": [
            316,
            0,
            400,
            24
        ],
        "label": "background",
        "max_iou": 0.0,
        "matched_gt": 0,
        "matches": []
    },
    {
        "box": [
            338,
            178,
            346,
            195
        ],
        "label": "background",
        "max_iou": 0.0,
        "matched_gt": 0,
        "matches": []
    },
    {
        "box": [
            328,
            17,
            400,
            63
        ],
        "label": "background",
        "max_iou": 0.0,
        "matched_gt": 0,
        "matches": []
    },
    {
        "box": [
            371,
            302,
            400,
            319
        ],
        "label": "background",
        "max_iou": 0.0,
        "matched_gt": 0,
        "matches": []
    },
    {
        "box": [
            228,
            223,
            260,
            260
        ],
        "label": "background",
        "max_iou": 0.09417004692595243,
        "matched_gt": 1,
        "matches": []
    },
    {
        "box": [
            240,
            148,
            257,
            160
        ],
        "label": "background",
        "max_iou": 0.0,
        "matched_gt": 0,
        "matches": []
    },
    {
        "box": [
            290,
            164,
            314,
            195
        ],
        "label": "background",
        "max_iou": 0.0,
        "matched_gt": 0,
        "matches": []
    },
    {
        "box": [
            145,
            142,
            182,
            188
        ],
        "label": "background",
        "max_iou": 0.26346749226006194,
        "matched_gt": 0,
        "matches": []
    },
    {
        "box": [
            283,
            230,
            319,
            257
        ],
        "label": "background",
        "max_iou": 0.0,
        "matched_gt": 0,
        "matches": []
    },
    {
        "box": [
            281,
            294,
            296,
            307
        ],
        "label": "background",
        "max_iou": 0.05480607082630692,
        "matched_gt": 2,
        "matches": []
    },
    {
        "box": [
            12,
            153,
            26,
            168
        ],
        "label": "background",
        "max_iou": 0.0,
        "matched_gt": 0,
        "matches": []
    },
    {
        "box": [
            246,
            249,
            277,
            298
        ],
        "label": "background",
        "max_iou": 0.12081444364908932,
        "matched_gt": 1,
        "matches": []
    },
    {
        "box": [
            5,
            300,
            26,
            322
        ],
        "label": "background",
        "max_iou": 0.0,
        "matched_gt": 0,
        "matches": []
    },
    {
        "box": [
            14,
            38,
            36,
            49
        ],
        "label": "background",
        "max_iou": 0.0,
        "matched_gt": 0,
        "matches": []
    },
    {
        "box": [
            355,
            286,
            384,
            311
        ],
        "label": "background",
        "max_iou": 0.0,
        "matched_gt": 0,
        "matches": []
    },
    {
        "box": [
            106,
            60,
            343,
            160
        ],
        "label": "background",
        "max_iou": 0.09022556390977443,
        "matched_gt": 0,
        "matches": []
    },
    {
        "box": [
            189,
            105,
            212,
            117
        ],
        "label": "background",
        "max_iou": 0.0,
        "matched_gt": 0,
        "matches": []
    },
    {
        "box": [
            308,
            303,
            355,
            322
        ],
        "label": "background",
        "max_iou": 0.056941431670282,
        "matched_gt": 2,
        "matches": []
    },
    {
        "box": [
            190,
            0,
            225,
            6
        ],
        "label": "background",
        "max_iou": 0.0,
        "matched_gt": 0,
        "matches": []
    },
    {
        "box": [
            201,
            297,
            267,
            358
        ],
        "label": "background",
        "max_iou": 0.028629856850715747,
        "matched_gt": 1,
        "matches": []
    },
    {
        "box": [
            201,
            80,
            350,
            148
        ],
        "label": "background",
        "max_iou": 0.0,
        "matched_gt": 0,
        "matches": []
    },
    {
        "box": [
            21,
            30,
            63,
            66
        ],
        "label": "background",
        "max_iou": 0.0,
        "matched_gt": 0,
        "matches": []
    },
    {
        "box": [
            0,
            363,
            30,
            400
        ],
        "label": "background",
        "max_iou": 0.0,
        "matched_gt": 0,
        "matches": []
    },
    {
        "box": [
            283,
            230,
            319,
            253
        ],
        "label": "background",
        "max_iou": 0.0,
        "matched_gt": 0,
        "matches": []
    },
    {
        "box": [
            216,
            364,
            237,
            391
        ],
        "label": "background",
        "max_iou": 0.0,
        "matched_gt": 0,
        "matches": []
    },
    {
        "box": [
            272,
            142,
            331,
            173
        ],
        "label": "background",
        "max_iou": 0.0,
        "matched_gt": 0,
        "matches": []
    },
    {
        "box": [
            220,
            196,
            275,
            227
        ],
        "label": "background",
        "max_iou": 0.09259259259259259,
        "matched_gt": 1,
        "matches": []
    },
    {
        "box": [
            201,
            247,
            400,
            400
        ],
        "label": "background",
        "max_iou": 0.1119727047146402,
        "matched_gt": 1,
        "matches": []
    },
    {
        "box": [
            336,
            364,
            400,
            400
        ],
        "label": "background",
        "max_iou": 0.0,
        "matched_gt": 0,
        "matches": []
    },
    {
        "box": [
            284,
            0,
            400,
            24
        ],
        "label": "background",
        "max_iou": 0.0,
        "matched_gt": 0,
        "matches": []
    },
    {
        "box": [
            240,
            196,
            266,
            204
        ],
        "label": "background",
        "max_iou": 0.0,
        "matched_gt": 0,
        "matches": []
    },
    {
        "box": [
            209,
            209,
            279,
            263
        ],
        "label": "background",
        "max_iou": 0.2895670688431512,
        "matched_gt": 1,
        "matches": []
    },
    {
        "box": [
            97,
            118,
            186,
            198
        ],
        "label": "pothole",
        "max_iou": 0.7719206680584552,
        "matched_gt": 0,
        "matches": [
            0
        ]
    },
    {
        "box": [
            137,
            70,
            226,
            139
        ],
        "label": "background",
        "max_iou": 0.04278384640847401,
        "matched_gt": 0,
        "matches": []
    },
    {
        "box": [
            196,
            264,
            215,
            276
        ],
        "label": "background",
        "max_iou": 0.018134096874254355,
        "matched_gt": 1,
        "matches": []
    },
    {
        "box": [
            97,
            118,
            181,
            187
        ],
        "label": "pothole",
        "max_iou": 0.6789041095890411,
        "matched_gt": 0,
        "matches": [
            0
        ]
    },
    {
        "box": [
            357,
            388,
            383,
            400
        ],
        "label": "background",
        "max_iou": 0.0,
        "matched_gt": 0,
        "matches": []
    },
    {
        "box": [
            179,
            203,
            283,
            264
        ],
        "label": "background",
        "max_iou": 0.4401979444232965,
        "matched_gt": 1,
        "matches": []
    },
    {
        "box": [
            85,
            133,
            263,
            310
        ],
        "label": "background",
        "max_iou": 0.34011309740970447,
        "matched_gt": 1,
        "matches": []
    },
    {
        "box": [
            264,
            321,
            277,
            342
        ],
        "label": "background",
        "max_iou": 0.0,
        "matched_gt": 0,
        "matches": []
    },
    {
        "box": [
            179,
            189,
            279,
            360
        ],
        "label": "background",
        "max_iou": 0.48580441640378547,
        "matched_gt": 1,
        "matches": []
    },
    {
        "box": [
            172,
            165,
            242,
            222
        ],
        "label": "background",
        "max_iou": 0.07740844337474793,
        "matched_gt": 1,
        "matches": []
    },
    {
        "box": [
            235,
            212,
            276,
            227
        ],
        "label": "background",
        "max_iou": 0.04891434025292293,
        "matched_gt": 1,
        "matches": []
    },
    {
        "box": [
            374,
            76,
            400,
            86
        ],
        "label": "background",
        "max_iou": 0.0,
        "matched_gt": 0,
        "matches": []
    },
    {
        "box": [
            85,
            133,
            270,
            310
        ],
        "label": "background",
        "max_iou": 0.35528440696213887,
        "matched_gt": 1,
        "matches": []
    },
    {
        "box": [
            354,
            186,
            375,
            207
        ],
        "label": "background",
        "max_iou": 0.0,
        "matched_gt": 0,
        "matches": []
    },
    {
        "box": [
            204,
            0,
            331,
            39
        ],
        "label": "background",
        "max_iou": 0.0,
        "matched_gt": 0,
        "matches": []
    },
    {
        "box": [
            249,
            135,
            321,
            169
        ],
        "label": "background",
        "max_iou": 0.0,
        "matched_gt": 0,
        "matches": []
    },
    {
        "box": [
            183,
            169,
            196,
            199
        ],
        "label": "background",
        "max_iou": 0.003957203576139528,
        "matched_gt": 0,
        "matches": []
    },
    {
        "box": [
            323,
            341,
            343,
            353
        ],
        "label": "background",
        "max_iou": 0.0,
        "matched_gt": 0,
        "matches": []
    },
    {
        "box": [
            350,
            369,
            368,
            383
        ],
        "label": "background",
        "max_iou": 0.0,
        "matched_gt": 0,
        "matches": []
    },
    {
        "box": [
            26,
            363,
            42,
            389
        ],
        "label": "background",
        "max_iou": 0.0,
        "matched_gt": 0,
        "matches": []
    },
    {
        "box": [
            14,
            30,
            45,
            49
        ],
        "label": "background",
        "max_iou": 0.0,
        "matched_gt": 0,
        "matches": []
    },
    {
        "box": [
            246,
            135,
            347,
            260
        ],
        "label": "background",
        "max_iou": 0.07257480951772868,
        "matched_gt": 1,
        "matches": []
    },
    {
        "box": [
            307,
            0,
            335,
            19
        ],
        "label": "background",
        "max_iou": 0.0,
        "matched_gt": 0,
        "matches": []
    },
    {
        "box": [
            309,
            352,
            323,
            368
        ],
        "label": "background",
        "max_iou": 0.0,
        "matched_gt": 0,
        "matches": []
    },
    {
        "box": [
            288,
            277,
            320,
            303
        ],
        "label": "pothole",
        "max_iou": 0.6649029982363316,
        "matched_gt": 2,
        "matches": [
            2
        ]
    },
    {
        "box": [
            330,
            81,
            345,
            88
        ],
        "label": "background",
        "max_iou": 0.0,
        "matched_gt": 0,
        "matches": []
    },
    {
        "box": [
            12,
            333,
            89,
            400
        ],
        "label": "background",
        "max_iou": 0.0,
        "matched_gt": 0,
        "matches": []
    },
    {
        "box": [
            106,
            61,
            223,
            136
        ],
        "label": "background",
        "max_iou": 0.042707549106837314,
        "matched_gt": 0,
        "matches": []
    },
    {
        "box": [
            249,
            161,
            314,
            195
        ],
        "label": "background",
        "max_iou": 0.0,
        "matched_gt": 0,
        "matches": []
    },
    {
        "box": [
            337,
            383,
            362,
            397
        ],
        "label": "background",
        "max_iou": 0.0,
        "matched_gt": 0,
        "matches": []
    },
    {
        "box": [
            75,
            157,
            95,
            176
        ],
        "label": "background",
        "max_iou": 0.01694915254237288,
        "matched_gt": 0,
        "matches": []
    },
    {
        "box": [
            191,
            203,
            222,
            216
        ],
        "label": "background",
        "max_iou": 0.02698852394143253,
        "matched_gt": 1,
        "matches": []
    },
    {
        "box": [
            62,
            204,
            98,
            248
        ],
        "label": "background",
        "max_iou": 0.0,
        "matched_gt": 0,
        "matches": []
    },
    {
        "box": [
            339,
            309,
            356,
            321
        ],
        "label": "background",
        "max_iou": 0.0,
        "matched_gt": 0,
        "matches": []
    },
    {
        "box": [
            191,
            196,
            279,
            264
        ],
        "label": "background",
        "max_iou": 0.37632574352888826,
        "matched_gt": 1,
        "matches": []
    },
    {
        "box": [
            156,
            187,
            174,
            198
        ],
        "label": "background",
        "max_iou": 0.024938423645320198,
        "matched_gt": 0,
        "matches": []
    },
    {
        "box": [
            246,
            178,
            347,
            260
        ],
        "label": "background",
        "max_iou": 0.08903394255874673,
        "matched_gt": 1,
        "matches": []
    },
    {
        "box": [
            178,
            196,
            253,
            243
        ],
        "label": "background",
        "max_iou": 0.2151268115942029,
        "matched_gt": 1,
        "matches": []
    },
    {
        "box": [
            179,
            91,
            343,
            160
        ],
        "label": "background",
        "max_iou": 0.009082652134423252,
        "matched_gt": 0,
        "matches": []
    },
    {
        "box": [
            228,
            223,
            277,
            298
        ],
        "label": "background",
        "max_iou": 0.2922930088284419,
        "matched_gt": 1,
        "matches": []
    },
    {
        "box": [
            66,
            210,
            90,
            237
        ],
        "label": "background",
        "max_iou": 0.0,
        "matched_gt": 0,
        "matches": []
    },
    {
        "box": [
            74,
            133,
            263,
            310
        ],
        "label": "background",
        "max_iou": 0.3211056574528546,
        "matched_gt": 1,
        "matches": []
    },
    {
        "box": [
            247,
            274,
            279,
            307
        ],
        "label": "background",
        "max_iou": 0.07070469007777516,
        "matched_gt": 1,
        "matches": []
    },
    {
        "box": [
            0,
            333,
            89,
            400
        ],
        "label": "background",
        "max_iou": 0.0,
        "matched_gt": 0,
        "matches": []
    },
    {
        "box": [
            75,
            157,
            263,
            310
        ],
        "label": "background",
        "max_iou": 0.371044776119403,
        "matched_gt": 1,
        "matches": []
    },
    {
        "box": [
            209,
            209,
            259,
            248
        ],
        "label": "background",
        "max_iou": 0.15509424958243856,
        "matched_gt": 1,
        "matches": []
    },
    {
        "box": [
            85,
            118,
            277,
            310
        ],
        "label": "background",
        "max_iou": 0.341064453125,
        "matched_gt": 1,
        "matches": []
    },
    {
        "box": [
            0,
            0,
            400,
            227
        ],
        "label": "background",
        "max_iou": 0.0711453744493392,
        "matched_gt": 0,
        "matches": []
    },
    {
        "box": [
            204,
            0,
            400,
            63
        ],
        "label": "background",
        "max_iou": 0.0,
        "matched_gt": 0,
        "matches": []
    },
    {
        "box": [
            336,
            355,
            400,
            400
        ],
        "label": "background",
        "max_iou": 0.0,
        "matched_gt": 0,
        "matches": []
    },
    {
        "box": [
            0,
            37,
            400,
            400
        ],
        "label": "background",
        "max_iou": 0.0865909090909091,
        "matched_gt": 1,
        "matches": []
    },
    {
        "box": [
            0,
            0,
            400,
            260
        ],
        "label": "background",
        "max_iou": 0.06373873051793992,
        "matched_gt": 1,
        "matches": []
    },
    {
        "box": [
            183,
            169,
            275,
            227
        ],
        "label": "background",
        "max_iou": 0.12741580107019201,
        "matched_gt": 1,
        "matches": []
    },
    {
        "box": [
            166,
            116,
            227,
            137
        ],
        "label": "background",
        "max_iou": 0.02137485156353081,
        "matched_gt": 0,
        "matches": []
    },
    {
        "box": [
            191,
            203,
            279,
            264
        ],
        "label": "background",
        "max_iou": 0.39434211548923603,
        "matched_gt": 1,
        "matches": []
    },
    {
        "box": [
            222,
            135,
            315,
            195
        ],
        "label": "background",
        "max_iou": 0.0,
        "matched_gt": 0,
        "matches": []
    },
    {
        "box": [
            166,
            91,
            343,
            174
        ],
        "label": "background",
        "max_iou": 0.04074201643458151,
        "matched_gt": 0,
        "matches": []
    },
    {
        "box": [
            141,
            133,
            182,
            188
        ],
        "label": "background",
        "max_iou": 0.34907120743034054,
        "matched_gt": 0,
        "matches": []
    },
    {
        "box": [
            307,
            0,
            400,
            24
        ],
        "label": "background",
        "max_iou": 0.0,
        "matched_gt": 0,
        "matches": []
    },
    {
        "box": [
            249,
            135,
            338,
            174
        ],
        "label": "background",
        "max_iou": 0.0,
        "matched_gt": 0,
        "matches": []
    },
    {
        "box": [
            155,
            143,
            187,
            166
        ],
        "label": "background",
        "max_iou": 0.10215959565017614,
        "matched_gt": 0,
        "matches": []
    },
    {
        "box": [
            315,
            13,
            400,
            63
        ],
        "label": "background",
        "max_iou": 0.0,
        "matched_gt": 0,
        "matches": []
    },
    {
        "box": [
            106,
            60,
            221,
            116
        ],
        "label": "background",
        "max_iou": 0.0,
        "matched_gt": 0,
        "matches": []
    },
    {
        "box": [
            328,
            107,
            391,
            135
        ],
        "label": "background",
        "max_iou": 0.0,
        "matched_gt": 0,
        "matches": []
    },
    {
        "box": [
            206,
            294,
            279,
            360
        ],
        "label": "background",
        "max_iou": 0.042563395479887293,
        "matched_gt": 1,
        "matches": []
    },
    {
        "box": [
            155,
            134,
            347,
            260
        ],
        "label": "background",
        "max_iou": 0.2232573615039095,
        "matched_gt": 1,
        "matches": []
    },
    {
        "box": [
            201,
            297,
            267,
            360
        ],
        "label": "background",
        "max_iou": 0.028397565922920892,
        "matched_gt": 1,
        "matches": []
    },
    {
        "box": [
            166,
            91,
            343,
            160
        ],
        "label": "background",
        "max_iou": 0.03182847985854009,
        "matched_gt": 0,
        "matches": []
    },
    {
        "box": [
            155,
            134,
            284,
            227
        ],
        "label": "background",
        "max_iou": 0.12263547473270583,
        "matched_gt": 1,
        "matches": []
    },
    {
        "box": [
            308,
            303,
            369,
            322
        ],
        "label": "background",
        "max_iou": 0.04976303317535545,
        "matched_gt": 2,
        "matches": []
    },
    {
        "box": [
            209,
            209,
            282,
            289
        ],
        "label": "background",
        "max_iou": 0.41933245972404226,
        "matched_gt": 1,
        "matches": []
    },
    {
        "box": [
            74,
            80,
            400,
            400
        ],
        "label": "background",
        "max_iou": 0.12052338957055214,
        "matched_gt": 1,
        "matches": []
    },
    {
        "box": [
            190,
            0,
            400,
            63
        ],
        "label": "background",
        "max_iou": 0.0,
        "matched_gt": 0,
        "matches": []
    },
    {
        "box": [
            206,
            278,
            279,
            360
        ],
        "label": "background",
        "max_iou": 0.11045294082450786,
        "matched_gt": 1,
        "matches": []
    },
    {
        "box": [
            5,
            290,
            50,
            322
        ],
        "label": "background",
        "max_iou": 0.0,
        "matched_gt": 0,
        "matches": []
    },
    {
        "box": [
            274,
            26,
            328,
            50
        ],
        "label": "background",
        "max_iou": 0.0,
        "matched_gt": 0,
        "matches": []
    },
    {
        "box": [
            231,
            113,
            400,
            320
        ],
        "label": "background",
        "max_iou": 0.10590205106739221,
        "matched_gt": 1,
        "matches": []
    },
    {
        "box": [
            247,
            278,
            279,
            314
        ],
        "label": "background",
        "max_iou": 0.06025492468134415,
        "matched_gt": 1,
        "matches": []
    },
    {
        "box": [
            178,
            196,
            282,
            289
        ],
        "label": "pothole",
        "max_iou": 0.5970277837604997,
        "matched_gt": 1,
        "matches": [
            1
        ]
    },
    {
        "box": [
            179,
            91,
            343,
            174
        ],
        "label": "background",
        "max_iou": 0.011591573430097772,
        "matched_gt": 0,
        "matches": []
    },
    {
        "box": [
            294,
            45,
            400,
            88
        ],
        "label": "background",
        "max_iou": 0.0,
        "matched_gt": 0,
        "matches": []
    },
    {
        "box": [
            93,
            130,
            400,
            385
        ],
        "label": "background",
        "max_iou": 0.16060547997700708,
        "matched_gt": 1,
        "matches": []
    },
    {
        "box": [
            138,
            137,
            181,
            187
        ],
        "label": "background",
        "max_iou": 0.3328173374613003,
        "matched_gt": 0,
        "matches": []
    },
    {
        "box": [
            179,
            189,
            218,
            222
        ],
        "label": "background",
        "max_iou": 0.050238690611502615,
        "matched_gt": 1,
        "matches": []
    },
    {
        "box": [
            179,
            189,
            240,
            230
        ],
        "label": "background",
        "max_iou": 0.11255443206140675,
        "matched_gt": 1,
        "matches": []
    },
    {
        "box": [
            93,
            129,
            282,
            360
        ],
        "label": "background",
        "max_iou": 0.28798185941043086,
        "matched_gt": 1,
        "matches": []
    },
    {
        "box": [
            206,
            228,
            400,
            400
        ],
        "label": "background",
        "max_iou": 0.13308669379701565,
        "matched_gt": 1,
        "matches": []
    },
    {
        "box": [
            356,
            71,
            400,
            89
        ],
        "label": "background",
        "max_iou": 0.0,
        "matched_gt": 0,
        "matches": []
    },
    {
        "box": [
            181,
            205,
            282,
            289
        ],
        "label": "pothole",
        "max_iou": 0.6206418840914338,
        "matched_gt": 1,
        "matches": [
            1
        ]
    },
    {
        "box": [
            93,
            130,
            222,
            215
        ],
        "label": "pothole",
        "max_iou": 0.5259654961029863,
        "matched_gt": 0,
        "matches": [
            0
        ]
    },
    {
        "box": [
            199,
            0,
            400,
            89
        ],
        "label": "background",
        "max_iou": 0.0,
        "matched_gt": 0,
        "matches": []
    },
    {
        "box": [
            75,
            118,
            277,
            310
        ],
        "label": "background",
        "max_iou": 0.32418007425742573,
        "matched_gt": 1,
        "matches": []
    },
    {
        "box": [
            97,
            118,
            242,
            222
        ],
        "label": "background",
        "max_iou": 0.37864823348694315,
        "matched_gt": 0,
        "matches": []
    },
    {
        "box": [
            183,
            169,
            347,
            260
        ],
        "label": "background",
        "max_iou": 0.2315582030725131,
        "matched_gt": 1,
        "matches": []
    },
    {
        "box": [
            181,
            205,
            277,
            298
        ],
        "label": "pothole",
        "max_iou": 0.7100930565497494,
        "matched_gt": 1,
        "matches": [
            1
        ]
    },
    {
        "box": [
            209,
            209,
            277,
            298
        ],
        "label": "background",
        "max_iou": 0.48134892229380416,
        "matched_gt": 1,
        "matches": []
    },
    {
        "box": [
            141,
            130,
            187,
            187
        ],
        "label": "background",
        "max_iou": 0.36962750716332377,
        "matched_gt": 0,
        "matches": []
    },
    {
        "box": [
            74,
            133,
            270,
            310
        ],
        "label": "background",
        "max_iou": 0.3357354811360746,
        "matched_gt": 1,
        "matches": []
    },
    {
        "box": [
            284,
            0,
            400,
            63
        ],
        "label": "background",
        "max_iou": 0.0,
        "matched_gt": 0,
        "matches": []
    },
    {
        "box": [
            75,
            118,
            263,
            310
        ],
        "label": "background",
        "max_iou": 0.2984632623659356,
        "matched_gt": 1,
        "matches": []
    },
    {
        "box": [
            168,
            134,
            314,
            208
        ],
        "label": "background",
        "max_iou": 0.06096361848574238,
        "matched_gt": 0,
        "matches": []
    },
    {
        "box": [
            181,
            205,
            282,
            360
        ],
        "label": "pothole",
        "max_iou": 0.5075838496047853,
        "matched_gt": 1,
        "matches": [
            1
        ]
    },
    {
        "box": [
            74,
            118,
            282,
            310
        ],
        "label": "background",
        "max_iou": 0.31482872596153844,
        "matched_gt": 1,
        "matches": []
    },
    {
        "box": [
            97,
            118,
            282,
            289
        ],
        "label": "background",
        "max_iou": 0.3180679785330948,
        "matched_gt": 1,
        "matches": []
    },
    {
        "box": [
            235,
            224,
            282,
            307
        ],
        "label": "background",
        "max_iou": 0.25621473234710995,
        "matched_gt": 1,
        "matches": []
    },
    {
        "box": [
            181,
            205,
            400,
            400
        ],
        "label": "background",
        "max_iou": 0.20762878489972472,
        "matched_gt": 1,
        "matches": []
    },
    {
        "box": [
            106,
            60,
            343,
            174
        ],
        "label": "background",
        "max_iou": 0.12004014720642356,
        "matched_gt": 0,
        "matches": []
    },
    {
        "box": [
            294,
            45,
            400,
            89
        ],
        "label": "background",
        "max_iou": 0.0,
        "matched_gt": 0,
        "matches": []
    },
    {
        "box": [
            311,
            45,
            400,
            89
        ],
        "label": "background",
        "max_iou": 0.0,
        "matched_gt": 0,
        "matches": []
    },
    {
        "box": [
            74,
            113,
            315,
            310
        ],
        "label": "background",
        "max_iou": 0.2648229669102934,
        "matched_gt": 1,
        "matches": []
    },
    {
        "box": [
            179,
            189,
            400,
            400
        ],
        "label": "background",
        "max_iou": 0.19599208112803523,
        "matched_gt": 1,
        "matches": []
    },
    {
        "box": [
            181,
            80,
            400,
            400
        ],
        "label": "background",
        "max_iou": 0.12992658819669442,
        "matched_gt": 1,
        "matches": []
    },
    {
        "box": [
            181,
            205,
            282,
            307
        ],
        "label": "pothole",
        "max_iou": 0.7107920125645053,
        "matched_gt": 1,
        "matches": [
            1
        ]
    },
    {
        "box": [
            201,
            80,
            400,
            400
        ],
        "label": "background",
        "max_iou": 0.10947343915959784,
        "matched_gt": 1,
        "matches": []
    },
    {
        "box": [
            97,
            113,
            315,
            227
        ],
        "label": "background",
        "max_iou": 0.23295007087730352,
        "matched_gt": 0,
        "matches": []
    },
    {
        "box": [
            168,
            134,
            347,
            260
        ],
        "label": "background",
        "max_iou": 0.20578745022655498,
        "matched_gt": 1,
        "matches": []
    },
    {
        "box": [
            106,
            60,
            347,
            260
        ],
        "label": "background",
        "max_iou": 0.12986167918494831,
        "matched_gt": 1,
        "matches": []
    },
    {
        "box": [
            75,
            60,
            400,
            400
        ],
        "label": "background",
        "max_iou": 0.11378280542986426,
        "matched_gt": 1,
        "matches": []
    },
    {
        "box": [
            253,
            247,
            400,
            400
        ],
        "label": "background",
        "max_iou": 0.04695211417900493,
        "matched_gt": 2,
        "matches": []
    },
    {
        "box": [
            0,
            17,
            400,
            400
        ],
        "label": "background",
        "max_iou": 0.08206919060052219,
        "matched_gt": 1,
        "matches": []
    },
    {
        "box": [
            75,
            118,
            400,
            400
        ],
        "label": "background",
        "max_iou": 0.1371849427168576,
        "matched_gt": 1,
        "matches": []
    },
    {
        "box": [
            267,
            228,
            400,
            400
        ],
        "label": "background",
        "max_iou": 0.04616191641895436,
        "matched_gt": 2,
        "matches": []
    },
    {
        "box": [
            75,
            60,
            347,
            310
        ],
        "label": "background",
        "max_iou": 0.18489705882352941,
        "matched_gt": 1,
        "matches": []
    }
]